{
  "generated_at": "2026-03-12T10:26:22.945280+00:00",
  "paper_object": "audited negative case study for a small claimed gain in training-free DLM revision",
  "allowed_claims": [
    "CARD-84 shows a localized GSM8K signal against the compute-matched DNB-84 baseline.",
    "That localized signal does not cleanly separate from budget-matched random targeting.",
    "Entropy may be described as a risk marker, not as a validated targeting rule.",
    "The current evidence is limited to the audited slice and current-only artifacts."
  ],
  "forbidden_claims": [
    "entropy-guided revision reliably improves DLM reasoning",
    "observer-guided controller is validated",
    "CARD-84 is the winning inference method",
    "this work establishes a new protocol paradigm",
    "the method almost works / is a near-win",
    "reasoning-code divergence is mechanistically explained"
  ],
  "required_disclosures": [
    "audited-slice scope only",
    "CARD-84 failed the stricter sham-control gate against RAND-84",
    "trajectory addon was skipped by the negative pivot",
    "runtime contract is a logged stable eager path, not a performance contribution"
  ],
  "evidence": {
    "decision_json": "current/exp/pilot_evidence_closure_v1/analysis/decision.json",
    "summary_md": "current/exp/pilot_evidence_closure_v1/analysis/summary.md",
    "proposal_md": "current/idea/proposal.md",
    "claim_to_asset_map": "current/exp/pilot_evidence_closure_v1/analysis/claim_to_asset_map.json"
  }
}