{
  "conv1.weight": {
    "r_t_mean": Infinity,
    "r_t_std": NaN,
    "r_t_min": 4.5233294471020734e-05,
    "r_t_max": Infinity,
    "delta_hat_mean": NaN,
    "delta_hat_std": NaN,
    "lambda_t_mean": 0.0001,
    "lambda_t_std": 0.0,
    "n_records": 1126
  },
  "layer1.0.conv1.weight": {
    "r_t_mean": 0.005363458176412715,
    "r_t_std": 0.005176201950420613,
    "r_t_min": 0.00011784706807623918,
    "r_t_max": 0.17386566064064055,
    "delta_hat_mean": 6.281034161741353e-07,
    "delta_hat_std": 5.544951550724451e-05,
    "lambda_t_mean": 0.0001,
    "lambda_t_std": 0.0,
    "n_records": 1126
  },
  "layer1.0.conv2.weight": {
    "r_t_mean": 0.0052824313754523435,
    "r_t_std": 0.011926210146266592,
    "r_t_min": 6.148105402956448e-05,
    "r_t_max": 0.40420236523619846,
    "delta_hat_mean": 8.236038785408208e-08,
    "delta_hat_std": 2.622556776929509e-05,
    "lambda_t_mean": 0.0001,
    "lambda_t_std": 0.0,
    "n_records": 1126
  },
  "layer1.0.conv3.weight": {
    "r_t_mean": 0.004934520983027012,
    "r_t_std": 0.0064708063443579015,
    "r_t_min": 6.957538566538301e-05,
    "r_t_max": 0.22047563842002169,
    "delta_hat_mean": -1.1860042696621774e-06,
    "delta_hat_std": 2.278837128322438e-05,
    "lambda_t_mean": 0.0001,
    "lambda_t_std": 0.0,
    "n_records": 1126
  },
  "layer1.0.downsample.0.weight": {
    "r_t_mean": 0.005400371802736311,
    "r_t_std": 0.007331198406216437,
    "r_t_min": 5.060443384024536e-05,
    "r_t_max": 0.24895757958541867,
    "delta_hat_mean": 8.540252821633811e-07,
    "delta_hat_std": 2.5164014419791372e-05,
    "lambda_t_mean": 0.0001,
    "lambda_t_std": 0.0,
    "n_records": 1126
  },
  "layer1.1.conv1.weight": {
    "r_t_mean": Infinity,
    "r_t_std": NaN,
    "r_t_min": 3.752950302588195e-05,
    "r_t_max": Infinity,
    "delta_hat_mean": NaN,
    "delta_hat_std": NaN,
    "lambda_t_mean": 0.0001,
    "lambda_t_std": 0.0,
    "n_records": 1126
  },
  "layer1.1.conv2.weight": {
    "r_t_mean": 0.0048426214621593595,
    "r_t_std": 0.007553511403448941,
    "r_t_min": 2.7130243374677795e-05,
    "r_t_max": 0.25570247429789383,
    "delta_hat_mean": 9.837936494441604e-08,
    "delta_hat_std": 2.2596678294473582e-05,
    "lambda_t_mean": 0.0001,
    "lambda_t_std": 0.0,
    "n_records": 1126
  },
  "layer1.1.conv3.weight": {
    "r_t_mean": 0.004535485049360613,
    "r_t_std": 0.004490348412369637,
    "r_t_min": 4.7739967390623206e-05,
    "r_t_max": 0.1522648206274663,
    "delta_hat_mean": -7.537392404575263e-07,
    "delta_hat_std": 1.8443172028944556e-05,
    "lambda_t_mean": 0.0001,
    "lambda_t_std": 0.0,
    "n_records": 1126
  },
  "layer1.2.conv1.weight": {
    "r_t_mean": 0.003974104655923679,
    "r_t_std": 0.0016892163238579946,
    "r_t_min": 1.6624102782575608e-05,
    "r_t_max": 0.037677393702413485,
    "delta_hat_mean": -2.267115167064699e-07,
    "delta_hat_std": 1.763995098002771e-05,
    "lambda_t_mean": 0.0001,
    "lambda_t_std": 0.0,
    "n_records": 1126
  },
  "layer1.2.conv2.weight": {
    "r_t_mean": 0.004968647747329478,
    "r_t_std": 0.005566952113793812,
    "r_t_min": 2.4358901123563907e-05,
    "r_t_max": 0.18761938285679924,
    "delta_hat_mean": 3.0607914348902533e-07,
    "delta_hat_std": 1.664929372364516e-05,
    "lambda_t_mean": 0.0001,
    "lambda_t_std": 0.0,
    "n_records": 1126
  },
  "layer1.2.conv3.weight": {
    "r_t_mean": 0.004448354890262139,
    "r_t_std": 0.002962247727044672,
    "r_t_min": 3.808169786637972e-05,
    "r_t_max": 0.09867428835000841,
    "delta_hat_mean": -1.1091291668992271e-08,
    "delta_hat_std": 1.0329866051377838e-05,
    "lambda_t_mean": 0.0001,
    "lambda_t_std": 0.0,
    "n_records": 1126
  },
  "layer2.0.conv1.weight": {
    "r_t_mean": 0.004546188027360535,
    "r_t_std": 0.001503813308582333,
    "r_t_min": 3.4961985884616444e-05,
    "r_t_max": 0.041183483066173955,
    "delta_hat_mean": -4.5846414119991966e-07,
    "delta_hat_std": 1.0017199972200432e-05,
    "lambda_t_mean": 0.0001,
    "lambda_t_std": 0.0,
    "n_records": 1126
  },
  "layer2.0.conv2.weight": {
    "r_t_mean": 0.004871799125856823,
    "r_t_std": 0.004349980248521965,
    "r_t_min": 3.777020878060394e-05,
    "r_t_max": 0.14803635895091702,
    "delta_hat_mean": -7.537923102423522e-08,
    "delta_hat_std": 5.041768719158505e-06,
    "lambda_t_mean": 0.0001,
    "lambda_t_std": 0.0,
    "n_records": 1126
  },
  "layer2.0.conv3.weight": {
    "r_t_mean": 0.0045619981813027405,
    "r_t_std": 0.0024801643269011142,
    "r_t_min": 5.1001904263826065e-05,
    "r_t_max": 0.08280837489265838,
    "delta_hat_mean": 7.176115959930522e-08,
    "delta_hat_std": 3.807290303672153e-06,
    "lambda_t_mean": 0.0001,
    "lambda_t_std": 0.0,
    "n_records": 1126
  },
  "layer2.0.downsample.0.weight": {
    "r_t_mean": 0.0045583584425425705,
    "r_t_std": 0.0016978465902412069,
    "r_t_min": 5.401289302218012e-05,
    "r_t_max": 0.05881482822335726,
    "delta_hat_mean": 1.6662468686833107e-08,
    "delta_hat_std": 5.086723620873763e-06,
    "lambda_t_mean": 0.0001,
    "lambda_t_std": 0.0,
    "n_records": 1126
  },
  "layer2.1.conv1.weight": {
    "r_t_mean": 0.003348903806350243,
    "r_t_std": 0.0011645676965267528,
    "r_t_min": 3.928902951565356e-05,
    "r_t_max": 0.020591855623977785,
    "delta_hat_mean": 2.904340668157332e-07,
    "delta_hat_std": 6.54499214734728e-06,
    "lambda_t_mean": 0.0001,
    "lambda_t_std": 0.0,
    "n_records": 1126
  },
  "layer2.1.conv2.weight": {
    "r_t_mean": 0.004476208538261844,
    "r_t_std": 0.0030319018566842522,
    "r_t_min": 5.625918641450133e-05,
    "r_t_max": 0.10300001734618312,
    "delta_hat_mean": 7.472717058543566e-08,
    "delta_hat_std": 5.016369300418859e-06,
    "lambda_t_mean": 0.0001,
    "lambda_t_std": 0.0,
    "n_records": 1126
  },
  "layer2.1.conv3.weight": {
    "r_t_mean": 0.0045871812557980495,
    "r_t_std": 0.0017158247674319749,
    "r_t_min": 7.399119531298767e-05,
    "r_t_max": 0.0583733957753762,
    "delta_hat_mean": -1.9963456797855302e-07,
    "delta_hat_std": 4.2432482726562575e-06,
    "lambda_t_mean": 0.0001,
    "lambda_t_std": 0.0,
    "n_records": 1126
  },
  "layer2.2.conv1.weight": {
    "r_t_mean": 0.0037550408203815807,
    "r_t_std": 0.0011049034966113384,
    "r_t_min": 2.9918726822262333e-05,
    "r_t_max": 0.014650158926544095,
    "delta_hat_mean": 8.616991836158962e-08,
    "delta_hat_std": 6.355611447573899e-06,
    "lambda_t_mean": 0.0001,
    "lambda_t_std": 0.0,
    "n_records": 1126
  },
  "layer2.2.conv2.weight": {
    "r_t_mean": 0.004950262863898488,
    "r_t_std": 0.0022707186795362677,
    "r_t_min": 6.918602517420719e-05,
    "r_t_max": 0.07810508360962246,
    "delta_hat_mean": -1.454878934066936e-07,
    "delta_hat_std": 3.584042952455814e-06,
    "lambda_t_mean": 0.0001,
    "lambda_t_std": 0.0,
    "n_records": 1126
  },
  "layer2.2.conv3.weight": {
    "r_t_mean": 0.004774443800942157,
    "r_t_std": 0.0012692389531961802,
    "r_t_min": 6.500412775984246e-05,
    "r_t_max": 0.04266856107494339,
    "delta_hat_mean": 9.174648527538058e-08,
    "delta_hat_std": 2.7851959735409014e-06,
    "lambda_t_mean": 0.0001,
    "lambda_t_std": 0.0,
    "n_records": 1126
  },
  "layer2.3.conv1.weight": {
    "r_t_mean": 0.003932617991829025,
    "r_t_std": 0.0010069906961001557,
    "r_t_min": 2.4764523358558597e-05,
    "r_t_max": 0.011532052082099526,
    "delta_hat_mean": -2.6099945295596262e-08,
    "delta_hat_std": 5.088997781232313e-06,
    "lambda_t_mean": 0.0001,
    "lambda_t_std": 0.0,
    "n_records": 1126
  },
  "layer2.3.conv2.weight": {
    "r_t_mean": 0.0050926111615335985,
    "r_t_std": 0.001761805573704078,
    "r_t_min": 7.17767450928602e-05,
    "r_t_max": 0.058520686774660866,
    "delta_hat_mean": -6.110334176270397e-09,
    "delta_hat_std": 3.783684328915823e-06,
    "lambda_t_mean": 0.0001,
    "lambda_t_std": 0.0,
    "n_records": 1126
  },
  "layer2.3.conv3.weight": {
    "r_t_mean": 0.004878606888540446,
    "r_t_std": 0.0009979625270127358,
    "r_t_min": 0.00012069186634461311,
    "r_t_max": 0.032460247211447274,
    "delta_hat_mean": 5.412273877579665e-08,
    "delta_hat_std": 2.622354915677022e-06,
    "lambda_t_mean": 0.0001,
    "lambda_t_std": 0.0,
    "n_records": 1126
  },
  "layer3.0.conv1.weight": {
    "r_t_mean": 0.004773790979867397,
    "r_t_std": 0.000665847657042852,
    "r_t_min": 4.716902700027858e-05,
    "r_t_max": 0.015315270728494576,
    "delta_hat_mean": 8.086308343459414e-08,
    "delta_hat_std": 2.075101973023193e-06,
    "lambda_t_mean": 0.0001,
    "lambda_t_std": 0.0,
    "n_records": 1126
  },
  "layer3.0.conv2.weight": {
    "r_t_mean": 0.005166845055700623,
    "r_t_std": 0.001680676614942374,
    "r_t_min": 0.00013475823466762034,
    "r_t_max": 0.05242557793983326,
    "delta_hat_mean": 4.598006880036824e-08,
    "delta_hat_std": 1.4601223871510402e-06,
    "lambda_t_mean": 0.0001,
    "lambda_t_std": 0.0,
    "n_records": 1126
  },
  "layer3.0.conv3.weight": {
    "r_t_mean": 0.005051775966846097,
    "r_t_std": 0.001115466416777803,
    "r_t_min": 0.00019225488884748665,
    "r_t_max": 0.029742333660582054,
    "delta_hat_mean": 1.0926840617439493e-08,
    "delta_hat_std": 1.4295185816595968e-06,
    "lambda_t_mean": 0.0001,
    "lambda_t_std": 0.0,
    "n_records": 1126
  },
  "layer3.0.downsample.0.weight": {
    "r_t_mean": 0.004666634819015043,
    "r_t_std": 0.0006837875451393392,
    "r_t_min": 0.0001651274212755548,
    "r_t_max": 0.02126510985587112,
    "delta_hat_mean": -3.926196701678885e-08,
    "delta_hat_std": 1.5861122985366086e-06,
    "lambda_t_mean": 0.0001,
    "lambda_t_std": 0.0,
    "n_records": 1126
  },
  "layer3.1.conv1.weight": {
    "r_t_mean": 0.003808411187962878,
    "r_t_std": 0.0008905977423596893,
    "r_t_min": 4.2139413081237684e-05,
    "r_t_max": 0.0074048164229691404,
    "delta_hat_mean": 5.986035925872657e-08,
    "delta_hat_std": 1.8598082510963148e-06,
    "lambda_t_mean": 0.0001,
    "lambda_t_std": 0.0,
    "n_records": 1126
  },
  "layer3.1.conv2.weight": {
    "r_t_mean": 0.005076085076690723,
    "r_t_std": 0.0014295583444043868,
    "r_t_min": 0.00018077900270637765,
    "r_t_max": 0.03817601225457682,
    "delta_hat_mean": -8.308046462010766e-09,
    "delta_hat_std": 1.50860151715832e-06,
    "lambda_t_mean": 0.0001,
    "lambda_t_std": 0.0,
    "n_records": 1126
  },
  "layer3.1.conv3.weight": {
    "r_t_mean": 0.004987433131946725,
    "r_t_std": 0.0009159309910465826,
    "r_t_min": 0.00020772058926136659,
    "r_t_max": 0.020919642698318672,
    "delta_hat_mean": 1.3683838610673775e-08,
    "delta_hat_std": 1.2724813510506984e-06,
    "lambda_t_mean": 0.0001,
    "lambda_t_std": 0.0,
    "n_records": 1126
  },
  "layer3.2.conv1.weight": {
    "r_t_mean": 0.004141748885884025,
    "r_t_std": 0.0006300878302145024,
    "r_t_min": 5.692567863571745e-05,
    "r_t_max": 0.006186134189340754,
    "delta_hat_mean": 3.7344174149312734e-08,
    "delta_hat_std": 1.290124907592151e-06,
    "lambda_t_mean": 0.0001,
    "lambda_t_std": 0.0,
    "n_records": 1126
  },
  "layer3.2.conv2.weight": {
    "r_t_mean": 0.005079630755831739,
    "r_t_std": 0.001421243999964422,
    "r_t_min": 0.0001913001320346936,
    "r_t_max": 0.02687250042346202,
    "delta_hat_mean": -6.02157259547333e-08,
    "delta_hat_std": 1.1891971201855605e-06,
    "lambda_t_mean": 0.0001,
    "lambda_t_std": 0.0,
    "n_records": 1126
  },
  "layer3.2.conv3.weight": {
    "r_t_mean": 0.005019884288607804,
    "r_t_std": 0.0010258913384768946,
    "r_t_min": 0.00020444136731020786,
    "r_t_max": 0.015319490780467434,
    "delta_hat_mean": -1.461820822043171e-08,
    "delta_hat_std": 9.505177685224567e-07,
    "lambda_t_mean": 0.0001,
    "lambda_t_std": 0.0,
    "n_records": 1126
  },
  "layer3.3.conv1.weight": {
    "r_t_mean": 0.004199706954057454,
    "r_t_std": 0.0006861918934577808,
    "r_t_min": 5.197564669216407e-05,
    "r_t_max": 0.006282704932776954,
    "delta_hat_mean": 1.9592094337450314e-08,
    "delta_hat_std": 1.221139895578774e-06,
    "lambda_t_mean": 0.0001,
    "lambda_t_std": 0.0,
    "n_records": 1126
  },
  "layer3.3.conv2.weight": {
    "r_t_mean": 0.005162377589928309,
    "r_t_std": 0.0012095985322998497,
    "r_t_min": 0.00016953738234640935,
    "r_t_max": 0.020434270589390745,
    "delta_hat_mean": -2.0749619673541308e-08,
    "delta_hat_std": 1.1756780719556156e-06,
    "lambda_t_mean": 0.0001,
    "lambda_t_std": 0.0,
    "n_records": 1126
  },
  "layer3.3.conv3.weight": {
    "r_t_mean": 0.005041797025212418,
    "r_t_std": 0.0008500580816478447,
    "r_t_min": 0.00020816891439737488,
    "r_t_max": 0.011727092535885095,
    "delta_hat_mean": 1.9173364604699914e-08,
    "delta_hat_std": 9.096134418279345e-07,
    "lambda_t_mean": 0.0001,
    "lambda_t_std": 0.0,
    "n_records": 1126
  },
  "layer3.4.conv1.weight": {
    "r_t_mean": 0.004310933097253109,
    "r_t_std": 0.0006435797859129951,
    "r_t_min": 6.994570990962559e-05,
    "r_t_max": 0.0062121707718184776,
    "delta_hat_mean": 3.8623023158659725e-08,
    "delta_hat_std": 1.2678387463843913e-06,
    "lambda_t_mean": 0.0001,
    "lambda_t_std": 0.0,
    "n_records": 1126
  },
  "layer3.4.conv2.weight": {
    "r_t_mean": 0.005161948731457241,
    "r_t_std": 0.0011641457279782613,
    "r_t_min": 0.00024768214065379286,
    "r_t_max": 0.016281078707073092,
    "delta_hat_mean": 1.1518454138292376e-08,
    "delta_hat_std": 1.0790037970174437e-06,
    "lambda_t_mean": 0.0001,
    "lambda_t_std": 0.0,
    "n_records": 1126
  },
  "layer3.4.conv3.weight": {
    "r_t_mean": 0.005038598615340473,
    "r_t_std": 0.0008087545637033138,
    "r_t_min": 0.00024344216663619244,
    "r_t_max": 0.009456349659880339,
    "delta_hat_mean": -6.1387355826204875e-09,
    "delta_hat_std": 9.213658053364339e-07,
    "lambda_t_mean": 0.0001,
    "lambda_t_std": 0.0,
    "n_records": 1126
  },
  "layer3.5.conv1.weight": {
    "r_t_mean": 0.004413854432193994,
    "r_t_std": 0.0005885397904173432,
    "r_t_min": 5.306633559547739e-05,
    "r_t_max": 0.006289839996154859,
    "delta_hat_mean": -8.024032196697748e-08,
    "delta_hat_std": 1.1937275354793323e-06,
    "lambda_t_mean": 0.0001,
    "lambda_t_std": 0.0,
    "n_records": 1126
  },
  "layer3.5.conv2.weight": {
    "r_t_mean": 0.0051434251164668545,
    "r_t_std": 0.001184163355122032,
    "r_t_min": 0.00019972668913380935,
    "r_t_max": 0.013352946144934803,
    "delta_hat_mean": 3.492659890935309e-08,
    "delta_hat_std": 9.550117007360406e-07,
    "lambda_t_mean": 0.0001,
    "lambda_t_std": 0.0,
    "n_records": 1126
  },
  "layer3.5.conv3.weight": {
    "r_t_mean": 0.00504136242633152,
    "r_t_std": 0.0008241870941874395,
    "r_t_min": 0.00023664380896175154,
    "r_t_max": 0.00897224770617652,
    "delta_hat_mean": -1.343038433909113e-08,
    "delta_hat_std": 7.841123019656821e-07,
    "lambda_t_mean": 0.0001,
    "lambda_t_std": 0.0,
    "n_records": 1126
  },
  "layer4.0.conv1.weight": {
    "r_t_mean": 0.0047652682918872796,
    "r_t_std": 0.0006558439938880972,
    "r_t_min": 6.735357654555154e-05,
    "r_t_max": 0.0062635078977937185,
    "delta_hat_mean": 2.097632643007644e-08,
    "delta_hat_std": 8.168902047058586e-07,
    "lambda_t_mean": 0.0001,
    "lambda_t_std": 0.0,
    "n_records": 1126
  },
  "layer4.0.conv2.weight": {
    "r_t_mean": 0.005246525877050877,
    "r_t_std": 0.0009414426739842431,
    "r_t_min": 0.0002715047044951045,
    "r_t_max": 0.01617841468435442,
    "delta_hat_mean": 1.6866280859369734e-09,
    "delta_hat_std": 4.6836469747855444e-07,
    "lambda_t_mean": 0.0001,
    "lambda_t_std": 0.0,
    "n_records": 1126
  },
  "layer4.0.conv3.weight": {
    "r_t_mean": 0.005269528547277119,
    "r_t_std": 0.0008086106695499002,
    "r_t_min": 0.0006559370373417134,
    "r_t_max": 0.010259330014188252,
    "delta_hat_mean": -1.92238958433072e-08,
    "delta_hat_std": 5.43133906708728e-07,
    "lambda_t_mean": 0.0001,
    "lambda_t_std": 0.0,
    "n_records": 1126
  },
  "layer4.0.downsample.0.weight": {
    "r_t_mean": 0.004851953181284138,
    "r_t_std": 0.0005086910643640115,
    "r_t_min": 0.0005267448671025477,
    "r_t_max": 0.00754111860381541,
    "delta_hat_mean": 1.6817380344490986e-08,
    "delta_hat_std": 6.335361313436905e-07,
    "lambda_t_mean": 0.0001,
    "lambda_t_std": 0.0,
    "n_records": 1126
  },
  "layer4.1.conv1.weight": {
    "r_t_mean": 0.004671670223023054,
    "r_t_std": 0.0006454140780159271,
    "r_t_min": 4.5547564083514297e-05,
    "r_t_max": 0.006329199246289125,
    "delta_hat_mean": -6.9616245419816e-09,
    "delta_hat_std": 5.193377306031091e-07,
    "lambda_t_mean": 0.0001,
    "lambda_t_std": 0.0,
    "n_records": 1126
  },
  "layer4.1.conv2.weight": {
    "r_t_mean": 0.005337793034225973,
    "r_t_std": 0.001292621495578296,
    "r_t_min": 0.00031134294962441024,
    "r_t_max": 0.013535923192105746,
    "delta_hat_mean": 1.700159386084831e-08,
    "delta_hat_std": 3.9638641582193683e-07,
    "lambda_t_mean": 0.0001,
    "lambda_t_std": 0.0,
    "n_records": 1126
  },
  "layer4.1.conv3.weight": {
    "r_t_mean": 0.005443605870513885,
    "r_t_std": 0.0011837067497522502,
    "r_t_min": 0.00046353604289342076,
    "r_t_max": 0.010177372179568697,
    "delta_hat_mean": -3.2400647420637154e-08,
    "delta_hat_std": 4.423633664519559e-07,
    "lambda_t_mean": 0.0001,
    "lambda_t_std": 0.0,
    "n_records": 1126
  },
  "layer4.2.conv1.weight": {
    "r_t_mean": 0.004862011699370463,
    "r_t_std": 0.001065500980877766,
    "r_t_min": 9.148610843410197e-05,
    "r_t_max": 0.007509835120815118,
    "delta_hat_mean": 2.0962756238382195e-08,
    "delta_hat_std": 4.405709788687843e-07,
    "lambda_t_mean": 0.0001,
    "lambda_t_std": 0.0,
    "n_records": 1126
  },
  "layer4.2.conv2.weight": {
    "r_t_mean": 0.005494516978163929,
    "r_t_std": 0.0008948979569558993,
    "r_t_min": 0.00040569670822548123,
    "r_t_max": 0.013020051697326849,
    "delta_hat_mean": -1.0504750158708602e-08,
    "delta_hat_std": 3.397185123374214e-07,
    "lambda_t_mean": 0.0001,
    "lambda_t_std": 0.0,
    "n_records": 1126
  },
  "layer4.2.conv3.weight": {
    "r_t_mean": 0.005552916398795852,
    "r_t_std": 0.0008783547258068907,
    "r_t_min": 0.0006266900811008162,
    "r_t_max": 0.012044758299488572,
    "delta_hat_mean": -1.948602640010805e-09,
    "delta_hat_std": 4.5594286152598914e-07,
    "lambda_t_mean": 0.0001,
    "lambda_t_std": 0.0,
    "n_records": 1126
  },
  "fc.weight": {
    "r_t_mean": 0.0052533538911913626,
    "r_t_std": 0.005575556954338597,
    "r_t_min": 0.0035668388065547107,
    "r_t_max": 0.17679101567915548,
    "delta_hat_mean": -0.0008595946473388434,
    "delta_hat_std": 0.001542557477756145,
    "lambda_t_mean": 0.0001,
    "lambda_t_std": 0.0,
    "n_records": 1126
  }
}