{
  "method": "FixedWD_bs1024",
  "seed": 123,
  "model": "vgg16_bn",
  "dataset": "cifar100",
  "epochs": [
    {
      "epoch": 0,
      "train_loss": 4.540171951055527,
      "test_loss": 4.394777312469483,
      "train_acc": 1.6398111979166667,
      "test_acc": 1.93,
      "lr": 0.8,
      "mean_rho_t": 0.007449093668680156,
      "std_rho_t": 0.00840883058478306,
      "mean_alpha_t": -0.01125774015956016,
      "mean_effective_wd": 6.444444444444444e-05,
      "total_wd_budget_epoch": 0.0029
    },
    {
      "epoch": 1,
      "train_loss": 4.3960311114788055,
      "test_loss": 4.3092994972229,
      "train_acc": 2.3111979166666665,
      "test_acc": 2.84,
      "lr": 0.7999506529926643,
      "mean_rho_t": 0.007027851949154489,
      "std_rho_t": 0.00840003731070546,
      "mean_alpha_t": -0.03654225596182433,
      "mean_effective_wd": 6.444444444444444e-05,
      "total_wd_budget_epoch": 0.0029
    },
    {
      "epoch": 2,
      "train_loss": 4.318520526091258,
      "test_loss": 4.242641510772705,
      "train_acc": 2.667236328125,
      "test_acc": 3.14,
      "lr": 0.7998026241462927,
      "mean_rho_t": 0.007974440410404014,
      "std_rho_t": 0.008757339389258986,
      "mean_alpha_t": -0.05910510610050525,
      "mean_effective_wd": 6.444444444444444e-05,
      "total_wd_budget_epoch": 0.0029
    },
    {
      "epoch": 3,
      "train_loss": 4.242397626241048,
      "test_loss": 4.259063262939453,
      "train_acc": 2.9622395833333335,
      "test_acc": 3.3,
      "lr": 0.7995559499847881,
      "mean_rho_t": 0.006289898928053188,
      "std_rho_t": 0.006752495229305709,
      "mean_alpha_t": -0.03666637419478995,
      "mean_effective_wd": 6.444444444444444e-05,
      "total_wd_budget_epoch": 0.0029
    },
    {
      "epoch": 4,
      "train_loss": 4.189988116423289,
      "test_loss": 4.068771261596679,
      "train_acc": 3.375244140625,
      "test_acc": 4.47,
      "lr": 0.7992106913713086,
      "mean_rho_t": 0.007560844749605856,
      "std_rho_t": 0.008825044338994873,
      "mean_alpha_t": 0.035812667249456545,
      "mean_effective_wd": 6.444444444444444e-05,
      "total_wd_budget_epoch": 0.0029
    },
    {
      "epoch": 5,
      "train_loss": 4.094952702522278,
      "test_loss": 4.011429949951172,
      "train_acc": 4.349772135416667,
      "test_acc": 5.12,
      "lr": 0.7987669334932512,
      "mean_rho_t": 0.005384243593803497,
      "std_rho_t": 0.005019152229239388,
      "mean_alpha_t": -0.050779814021697796,
      "mean_effective_wd": 6.444444444444444e-05,
      "total_wd_budget_epoch": 0.0029
    },
    {
      "epoch": 6,
      "train_loss": 4.012106637159984,
      "test_loss": 4.039322857284546,
      "train_acc": 5.312093098958333,
      "test_acc": 4.88,
      "lr": 0.798224785841232,
      "mean_rho_t": 0.00635906603038521,
      "std_rho_t": 0.007642807147631238,
      "mean_alpha_t": 0.024846929030715486,
      "mean_effective_wd": 6.444444444444444e-05,
      "total_wd_budget_epoch": 0.0029
    },
    {
      "epoch": 7,
      "train_loss": 3.966986025373141,
      "test_loss": 3.8846561756134035,
      "train_acc": 5.991617838541667,
      "test_acc": 7.13,
      "lr": 0.797584382182072,
      "mean_rho_t": 0.006371975379784741,
      "std_rho_t": 0.006967424122031143,
      "mean_alpha_t": -0.004743869515919948,
      "mean_effective_wd": 6.444444444444444e-05,
      "total_wd_budget_epoch": 0.0029
    },
    {
      "epoch": 8,
      "train_loss": 3.869787633419037,
      "test_loss": 3.7823884567260744,
      "train_acc": 6.770833333333333,
      "test_acc": 8.4,
      "lr": 0.7968458805257912,
      "mean_rho_t": 0.005202023423893081,
      "std_rho_t": 0.004592495249145254,
      "mean_alpha_t": -0.04092527994410515,
      "mean_effective_wd": 6.444444444444444e-05,
      "total_wd_budget_epoch": 0.0029
    },
    {
      "epoch": 9,
      "train_loss": 3.7542853951454163,
      "test_loss": 3.7934591552734376,
      "train_acc": 7.883707682291667,
      "test_acc": 8.38,
      "lr": 0.796009463086623,
      "mean_rho_t": 0.006027637948763884,
      "std_rho_t": 0.0055618066046845,
      "mean_alpha_t": -0.019434964243666503,
      "mean_effective_wd": 6.444444444444444e-05,
      "total_wd_budget_epoch": 0.0029
    },
    {
      "epoch": 10,
      "train_loss": 3.6638763596614203,
      "test_loss": 3.572824287033081,
      "train_acc": 8.900960286458334,
      "test_acc": 9.96,
      "lr": 0.7950753362380552,
      "mean_rho_t": 0.007114489714449273,
      "std_rho_t": 0.006603834210698919,
      "mean_alpha_t": -0.02853403956829168,
      "mean_effective_wd": 6.444444444444444e-05,
      "total_wd_budget_epoch": 0.0029
    },
    {
      "epoch": 11,
      "train_loss": 3.5429393500089645,
      "test_loss": 3.8432856113433838,
      "train_acc": 10.251871744791666,
      "test_acc": 10.18,
      "lr": 0.7940437304619096,
      "mean_rho_t": 0.006079439413382501,
      "std_rho_t": 0.006100881354977765,
      "mean_alpha_t": -0.04351189890260294,
      "mean_effective_wd": 6.444444444444444e-05,
      "total_wd_budget_epoch": 0.0029
    },
    {
      "epoch": 12,
      "train_loss": 3.43963386118412,
      "test_loss": 3.4737486766815184,
      "train_acc": 11.773681640625,
      "test_acc": 11.54,
      "lr": 0.7929149002914756,
      "mean_rho_t": 0.014293217929771625,
      "std_rho_t": 0.009663064685195174,
      "mean_alpha_t": -0.04311845995718484,
      "mean_effective_wd": 6.444444444444444e-05,
      "total_wd_budget_epoch": 0.0029
    },
    {
      "epoch": 13,
      "train_loss": 3.3813018749157586,
      "test_loss": 3.3439035957336425,
      "train_acc": 12.742106119791666,
      "test_acc": 14.84,
      "lr": 0.7916891242487063,
      "mean_rho_t": 0.006407151759975679,
      "std_rho_t": 0.007555748905696706,
      "mean_alpha_t": -0.005622367337333705,
      "mean_effective_wd": 6.444444444444444e-05,
      "total_wd_budget_epoch": 0.0029
    },
    {
      "epoch": 14,
      "train_loss": 3.257825717329979,
      "test_loss": 3.128450161743164,
      "train_acc": 14.849853515625,
      "test_acc": 17.77,
      "lr": 0.790366704775499,
      "mean_rho_t": 0.005522951436815132,
      "std_rho_t": 0.005971072469378283,
      "mean_alpha_t": -0.018668086613156294,
      "mean_effective_wd": 6.444444444444444e-05,
      "total_wd_budget_epoch": 0.0029
    },
    {
      "epoch": 15,
      "train_loss": 3.1401583552360535,
      "test_loss": 3.276487837982178,
      "train_acc": 17.071533203125,
      "test_acc": 17.77,
      "lr": 0.7889479681590706,
      "mean_rho_t": 0.006525848250959757,
      "std_rho_t": 0.008752858340235644,
      "mean_alpha_t": -0.006850682560312967,
      "mean_effective_wd": 6.444444444444444e-05,
      "total_wd_budget_epoch": 0.0029
    },
    {
      "epoch": 16,
      "train_loss": 3.0012350231409073,
      "test_loss": 2.9575016773223877,
      "train_acc": 19.834391276041668,
      "test_acc": 22.09,
      "lr": 0.7874332644514525,
      "mean_rho_t": 0.0059543418783446515,
      "std_rho_t": 0.005461566046578012,
      "mean_alpha_t": -0.00406263738986055,
      "mean_effective_wd": 6.444444444444444e-05,
      "total_wd_budget_epoch": 0.0029
    },
    {
      "epoch": 17,
      "train_loss": 2.8980491707722345,
      "test_loss": 2.9162745346069334,
      "train_acc": 22.054036458333332,
      "test_acc": 21.93,
      "lr": 0.7858229673831193,
      "mean_rho_t": 0.005933671024995423,
      "std_rho_t": 0.005981665638363445,
      "mean_alpha_t": -0.03018261415055825,
      "mean_effective_wd": 6.444444444444444e-05,
      "total_wd_budget_epoch": 0.0029
    },
    {
      "epoch": 18,
      "train_loss": 2.802913377682368,
      "test_loss": 3.2202688053131103,
      "train_acc": 24.053955078125,
      "test_acc": 21.42,
      "lr": 0.7841174742707773,
      "mean_rho_t": 0.0056055612359306685,
      "std_rho_t": 0.005696281922197244,
      "mean_alpha_t": -0.02361785698818341,
      "mean_effective_wd": 6.444444444444444e-05,
      "total_wd_budget_epoch": 0.0029
    },
    {
      "epoch": 19,
      "train_loss": 2.7070857137441635,
      "test_loss": 2.7110499786376954,
      "train_acc": 26.314290364583332,
      "test_acc": 26.64,
      "lr": 0.7823172059193321,
      "mean_rho_t": 0.005825074797541094,
      "std_rho_t": 0.005556710037787203,
      "mean_alpha_t": -0.03249543035706173,
      "mean_effective_wd": 6.444444444444444e-05,
      "total_wd_budget_epoch": 0.0029
    },
    {
      "epoch": 20,
      "train_loss": 2.6099470456441245,
      "test_loss": 2.722646161270142,
      "train_acc": 28.072102864583332,
      "test_acc": 27.83,
      "lr": 0.7804226065180615,
      "mean_rho_t": 0.006055264016911834,
      "std_rho_t": 0.006490930965005502,
      "mean_alpha_t": 0.0007754259602165648,
      "mean_effective_wd": 6.444444444444444e-05,
      "total_wd_budget_epoch": 0.0029
    },
    {
      "epoch": 21,
      "train_loss": 2.538614590962728,
      "test_loss": 2.735612614822388,
      "train_acc": 30.1513671875,
      "test_acc": 28.68,
      "lr": 0.7784341435310181,
      "mean_rho_t": 0.006645366161673026,
      "std_rho_t": 0.006405121432631493,
      "mean_alpha_t": -0.010506379542382354,
      "mean_effective_wd": 6.444444444444444e-05,
      "total_wd_budget_epoch": 0.0029
    },
    {
      "epoch": 22,
      "train_loss": 2.478001832962036,
      "test_loss": 2.6544155017852784,
      "train_acc": 31.243896484375,
      "test_acc": 30.08,
      "lr": 0.7763523075816903,
      "mean_rho_t": 0.0050805847227597956,
      "std_rho_t": 0.005418986111567042,
      "mean_alpha_t": -0.003556304740952301,
      "mean_effective_wd": 6.444444444444444e-05,
      "total_wd_budget_epoch": 0.0029
    },
    {
      "epoch": 23,
      "train_loss": 2.4299589544534683,
      "test_loss": 2.7640919734954834,
      "train_acc": 32.8857421875,
      "test_acc": 29.28,
      "lr": 0.774177612331947,
      "mean_rho_t": 0.0056208569403817365,
      "std_rho_t": 0.0058153251053909335,
      "mean_alpha_t": -0.006737002729425203,
      "mean_effective_wd": 6.444444444444444e-05,
      "total_wd_budget_epoch": 0.0029
    },
    {
      "epoch": 24,
      "train_loss": 2.3339445739984512,
      "test_loss": 2.526694509887695,
      "train_acc": 35.19287109375,
      "test_acc": 33.5,
      "lr": 0.7719105943553006,
      "mean_rho_t": 0.005729883783496663,
      "std_rho_t": 0.0046704481852559085,
      "mean_alpha_t": -0.017093544930274564,
      "mean_effective_wd": 6.444444444444444e-05,
      "total_wd_budget_epoch": 0.0029
    },
    {
      "epoch": 25,
      "train_loss": 2.2318734476963678,
      "test_loss": 2.282866481399536,
      "train_acc": 37.5732421875,
      "test_acc": 38.41,
      "lr": 0.7695518130045147,
      "mean_rho_t": 0.0053826305501646346,
      "std_rho_t": 0.00631641961012789,
      "mean_alpha_t": -0.011990725763271965,
      "mean_effective_wd": 6.444444444444444e-05,
      "total_wd_budget_epoch": 0.0029
    },
    {
      "epoch": 26,
      "train_loss": 2.1846570819616318,
      "test_loss": 2.2741733207702635,
      "train_acc": 38.877360026041664,
      "test_acc": 39.44,
      "lr": 0.7671018502735925,
      "mean_rho_t": 0.005361929550631624,
      "std_rho_t": 0.005876413560368169,
      "mean_alpha_t": -0.008407979937042221,
      "mean_effective_wd": 6.444444444444444e-05,
      "total_wd_budget_epoch": 0.0029
    },
    {
      "epoch": 27,
      "train_loss": 2.155109112461408,
      "test_loss": 2.5404336246490478,
      "train_acc": 39.992268880208336,
      "test_acc": 35.01,
      "lr": 0.7645613106541781,
      "mean_rho_t": 0.005466751036099218,
      "std_rho_t": 0.005424920379235903,
      "mean_alpha_t": -0.006646973979898279,
      "mean_effective_wd": 6.444444444444444e-05,
      "total_wd_budget_epoch": 0.0029
    },
    {
      "epoch": 28,
      "train_loss": 2.2519789139429727,
      "test_loss": 2.627609871673584,
      "train_acc": 38.633219401041664,
      "test_acc": 33.12,
      "lr": 0.7619308209864079,
      "mean_rho_t": 0.005810970473200452,
      "std_rho_t": 0.0049678735945658725,
      "mean_alpha_t": 0.0025436303238319078,
      "mean_effective_wd": 6.444444444444444e-05,
      "total_wd_budget_epoch": 0.0029
    },
    {
      "epoch": 29,
      "train_loss": 2.148430044452349,
      "test_loss": 2.276435764312744,
      "train_acc": 40.254720052083336,
      "test_acc": 39.21,
      "lr": 0.7592110303042463,
      "mean_rho_t": 0.0046514568906384215,
      "std_rho_t": 0.004357886048109059,
      "mean_alpha_t": -0.0019310018263292755,
      "mean_effective_wd": 6.444444444444444e-05,
      "total_wd_budget_epoch": 0.0029
    },
    {
      "epoch": 30,
      "train_loss": 2.015762428442637,
      "test_loss": 2.4038823417663573,
      "train_acc": 43.51806640625,
      "test_acc": 39.34,
      "lr": 0.7564026096753471,
      "mean_rho_t": 0.005247129812935717,
      "std_rho_t": 0.004799219469421655,
      "mean_alpha_t": -0.009164907221047592,
      "mean_effective_wd": 6.444444444444444e-05,
      "total_wd_budget_epoch": 0.0029
    },
    {
      "epoch": 31,
      "train_loss": 1.952216036617756,
      "test_loss": 2.261655974197388,
      "train_acc": 45.7275390625,
      "test_acc": 40.48,
      "lr": 0.7535062520354775,
      "mean_rho_t": 0.005010100287087302,
      "std_rho_t": 0.0055736600160907306,
      "mean_alpha_t": 0.008128839218028707,
      "mean_effective_wd": 6.444444444444444e-05,
      "total_wd_budget_epoch": 0.0029
    },
    {
      "epoch": 32,
      "train_loss": 1.9283616542816162,
      "test_loss": 2.1699084197998046,
      "train_acc": 46.08154296875,
      "test_acc": 42.05,
      "lr": 0.7505226720175454,
      "mean_rho_t": 0.004642619687751384,
      "std_rho_t": 0.004445058247369838,
      "mean_alpha_t": 0.00544997437325822,
      "mean_effective_wd": 6.444444444444444e-05,
      "total_wd_budget_epoch": 0.0029
    },
    {
      "epoch": 33,
      "train_loss": 1.8598728229602177,
      "test_loss": 2.2109392124176024,
      "train_acc": 47.591145833333336,
      "test_acc": 41.4,
      "lr": 0.7474526057752766,
      "mean_rho_t": 0.004453744034315884,
      "std_rho_t": 0.004385919425618194,
      "mean_alpha_t": 0.010732180059909334,
      "mean_effective_wd": 6.444444444444444e-05,
      "total_wd_budget_epoch": 0.0029
    },
    {
      "epoch": 34,
      "train_loss": 1.8286017800370853,
      "test_loss": 2.3774550788879396,
      "train_acc": 48.390706380208336,
      "test_acc": 40.3,
      "lr": 0.7442968108015775,
      "mean_rho_t": 0.005041631796377636,
      "std_rho_t": 0.004825107604535508,
      "mean_alpha_t": -0.006999826176786353,
      "mean_effective_wd": 6.444444444444444e-05,
      "total_wd_budget_epoch": 0.0029
    },
    {
      "epoch": 35,
      "train_loss": 1.7715402071674664,
      "test_loss": 2.0453353748321534,
      "train_acc": 50.197347005208336,
      "test_acc": 46.45,
      "lr": 0.741056065741637,
      "mean_rho_t": 0.005301947247091224,
      "std_rho_t": 0.005886189153880407,
      "mean_alpha_t": 0.004186694233292712,
      "mean_effective_wd": 6.444444444444444e-05,
      "total_wd_budget_epoch": 0.0029
    },
    {
      "epoch": 36,
      "train_loss": 1.7215191374222438,
      "test_loss": 1.9687860273361206,
      "train_acc": 51.798502604166664,
      "test_acc": 47.28,
      "lr": 0.737731170200806,
      "mean_rho_t": 0.005197548101032862,
      "std_rho_t": 0.004282329829595022,
      "mean_alpha_t": -0.01163074594575269,
      "mean_effective_wd": 6.444444444444444e-05,
      "total_wd_budget_epoch": 0.0029
    },
    {
      "epoch": 37,
      "train_loss": 1.7015382374326389,
      "test_loss": 2.171870084762573,
      "train_acc": 52.138264973958336,
      "test_acc": 45.27,
      "lr": 0.7343229445473082,
      "mean_rho_t": 0.005117582512959685,
      "std_rho_t": 0.004660177899686648,
      "mean_alpha_t": 0.0007219766350410671,
      "mean_effective_wd": 6.444444444444444e-05,
      "total_wd_budget_epoch": 0.0029
    },
    {
      "epoch": 38,
      "train_loss": 1.6512702703475952,
      "test_loss": 2.1597454544067385,
      "train_acc": 53.946940104166664,
      "test_acc": 45.58,
      "lr": 0.7308322297098248,
      "mean_rho_t": 0.004770706596448503,
      "std_rho_t": 0.004236028683580686,
      "mean_alpha_t": 0.012031049507120176,
      "mean_effective_wd": 6.444444444444444e-05,
      "total_wd_budget_epoch": 0.0029
    },
    {
      "epoch": 39,
      "train_loss": 1.6034227311611176,
      "test_loss": 2.0345187490463257,
      "train_acc": 54.878743489583336,
      "test_acc": 47.21,
      "lr": 0.7272598869700094,
      "mean_rho_t": 0.004597289070801731,
      "std_rho_t": 0.004493275194738918,
      "mean_alpha_t": 0.00035606944692803953,
      "mean_effective_wd": 6.444444444444444e-05,
      "total_wd_budget_epoch": 0.0029
    },
    {
      "epoch": 40,
      "train_loss": 1.5573459068934123,
      "test_loss": 2.1648955486297607,
      "train_acc": 56.25,
      "test_acc": 45.84,
      "lr": 0.723606797749979,
      "mean_rho_t": 0.004762307330288089,
      "std_rho_t": 0.004524522246406552,
      "mean_alpha_t": 0.010672098789147738,
      "mean_effective_wd": 6.444444444444444e-05,
      "total_wd_budget_epoch": 0.0029
    },
    {
      "epoch": 41,
      "train_loss": 1.5228639915585518,
      "test_loss": 1.8902811935424804,
      "train_acc": 57.330322265625,
      "test_acc": 50.9,
      "lr": 0.7198738633948363,
      "mean_rho_t": 0.004148250410391516,
      "std_rho_t": 0.004003892872233,
      "mean_alpha_t": 0.010809997341035054,
      "mean_effective_wd": 6.444444444444444e-05,
      "total_wd_budget_epoch": 0.0029
    },
    {
      "epoch": 42,
      "train_loss": 1.4984036087989807,
      "test_loss": 2.0596242755889893,
      "train_acc": 57.991536458333336,
      "test_acc": 48.9,
      "lr": 0.7160620049502762,
      "mean_rho_t": 0.004292014034154195,
      "std_rho_t": 0.0035602751516371446,
      "mean_alpha_t": 0.0005309705130567866,
      "mean_effective_wd": 6.444444444444444e-05,
      "total_wd_budget_epoch": 0.0029
    },
    {
      "epoch": 43,
      "train_loss": 1.4768682643771172,
      "test_loss": 2.037346106529236,
      "train_acc": 58.913167317708336,
      "test_acc": 49.77,
      "lr": 0.7121721629353319,
      "mean_rho_t": 0.004724032622444342,
      "std_rho_t": 0.004481554250132176,
      "mean_alpha_t": -0.01262071107754844,
      "mean_effective_wd": 6.444444444444444e-05,
      "total_wd_budget_epoch": 0.0029
    },
    {
      "epoch": 44,
      "train_loss": 1.4443822304407756,
      "test_loss": 1.8687671127319336,
      "train_acc": 59.537760416666664,
      "test_acc": 52.03,
      "lr": 0.7082052971103158,
      "mean_rho_t": 0.004382654301352092,
      "std_rho_t": 0.0036740172819884455,
      "mean_alpha_t": -0.007623870478470995,
      "mean_effective_wd": 6.444444444444444e-05,
      "total_wd_budget_epoch": 0.0029
    },
    {
      "epoch": 45,
      "train_loss": 1.4079656501611073,
      "test_loss": 1.8273869913101197,
      "train_acc": 60.585530598958336,
      "test_acc": 53.4,
      "lr": 0.7041623862400125,
      "mean_rho_t": 0.00478255495322357,
      "std_rho_t": 0.0036527918277126804,
      "mean_alpha_t": -0.000529521029781422,
      "mean_effective_wd": 6.444444444444444e-05,
      "total_wd_budget_epoch": 0.0029
    },
    {
      "epoch": 46,
      "train_loss": 1.3562687635421753,
      "test_loss": 1.9209941787719726,
      "train_acc": 62.162272135416664,
      "test_acc": 51.52,
      "lr": 0.7000444278521839,
      "mean_rho_t": 0.004342295321153685,
      "std_rho_t": 0.0033922100985057553,
      "mean_alpha_t": -0.0010198648483686647,
      "mean_effective_wd": 6.444444444444444e-05,
      "total_wd_budget_epoch": 0.0029
    },
    {
      "epoch": 47,
      "train_loss": 1.3100705320636432,
      "test_loss": 1.8495412675857543,
      "train_acc": 63.507080078125,
      "test_acc": 53.32,
      "lr": 0.6958524379914439,
      "mean_rho_t": 0.004631941570882984,
      "std_rho_t": 0.003919066506609057,
      "mean_alpha_t": -0.002643126453965992,
      "mean_effective_wd": 6.444444444444444e-05,
      "total_wd_budget_epoch": 0.0029
    },
    {
      "epoch": 48,
      "train_loss": 1.2933648601174355,
      "test_loss": 1.752677596282959,
      "train_acc": 63.85498046875,
      "test_acc": 55.7,
      "lr": 0.6915874509685647,
      "mean_rho_t": 0.004200550970026775,
      "std_rho_t": 0.003979523625446596,
      "mean_alpha_t": -0.006849252873210611,
      "mean_effective_wd": 6.444444444444444e-05,
      "total_wd_budget_epoch": 0.0029
    },
    {
      "epoch": 49,
      "train_loss": 1.2686234985788662,
      "test_loss": 2.185904104614258,
      "train_acc": 64.26595052083333,
      "test_acc": 47.57,
      "lr": 0.6872505191052756,
      "mean_rho_t": 0.004272002772170904,
      "std_rho_t": 0.003712209904359389,
      "mean_alpha_t": 0.004661048282069632,
      "mean_effective_wd": 6.444444444444444e-05,
      "total_wd_budget_epoch": 0.0029
    },
    {
      "epoch": 50,
      "train_loss": 1.321928250292937,
      "test_loss": 2.0317344038009644,
      "train_acc": 63.551839192708336,
      "test_acc": 51.62,
      "lr": 0.682842712474619,
      "mean_rho_t": 0.004518241748994883,
      "std_rho_t": 0.0038584812458575227,
      "mean_alpha_t": 0.008646287956630215,
      "mean_effective_wd": 6.444444444444444e-05,
      "total_wd_budget_epoch": 0.0029
    },
    {
      "epoch": 51,
      "train_loss": 1.2552136530478795,
      "test_loss": 2.028594421195984,
      "train_acc": 65.11433919270833,
      "test_acc": 50.78,
      "lr": 0.6783651186369257,
      "mean_rho_t": 0.00396530857645938,
      "std_rho_t": 0.003485800928499408,
      "mean_alpha_t": -0.00234368669884854,
      "mean_effective_wd": 6.444444444444444e-05,
      "total_wd_budget_epoch": 0.0029
    },
    {
      "epoch": 52,
      "train_loss": 1.2104212939739227,
      "test_loss": 1.8508588579177856,
      "train_acc": 66.29231770833333,
      "test_acc": 54.39,
      "lr": 0.6738188423714755,
      "mean_rho_t": 0.00396057061400436,
      "std_rho_t": 0.0034054531796866576,
      "mean_alpha_t": 0.005377295990858283,
      "mean_effective_wd": 6.444444444444444e-05,
      "total_wd_budget_epoch": 0.0029
    },
    {
      "epoch": 53,
      "train_loss": 1.200930615266164,
      "test_loss": 1.8412593421936034,
      "train_acc": 66.70939127604167,
      "test_acc": 54.27,
      "lr": 0.6692050054039094,
      "mean_rho_t": 0.004738755278404111,
      "std_rho_t": 0.0038952987467850797,
      "mean_alpha_t": -0.0023112834596875293,
      "mean_effective_wd": 6.444444444444444e-05,
      "total_wd_budget_epoch": 0.0029
    },
    {
      "epoch": 54,
      "train_loss": 1.1729346389571826,
      "test_loss": 1.9427774826049804,
      "train_acc": 67.24039713541667,
      "test_acc": 53.44,
      "lr": 0.6645247461294608,
      "mean_rho_t": 0.003965132811655369,
      "std_rho_t": 0.0032259271244912627,
      "mean_alpha_t": 0.007207994957845199,
      "mean_effective_wd": 6.444444444444444e-05,
      "total_wd_budget_epoch": 0.0029
    },
    {
      "epoch": 55,
      "train_loss": 1.1391817033290863,
      "test_loss": 1.9304818828582764,
      "train_acc": 68.524169921875,
      "test_acc": 53.66,
      "lr": 0.6597792193320735,
      "mean_rho_t": 0.0037687530386267235,
      "std_rho_t": 0.003239688891060716,
      "mean_alpha_t": 0.0022463537366100347,
      "mean_effective_wd": 6.444444444444444e-05,
      "total_wd_budget_epoch": 0.0029
    },
    {
      "epoch": 56,
      "train_loss": 1.110499121248722,
      "test_loss": 1.7939727783203125,
      "train_acc": 69.3115234375,
      "test_acc": 55.44,
      "lr": 0.6549695958994759,
      "mean_rho_t": 0.003470750968452091,
      "std_rho_t": 0.003056630570025776,
      "mean_alpha_t": 0.0009029993600564319,
      "mean_effective_wd": 6.444444444444444e-05,
      "total_wd_budget_epoch": 0.0029
    },
    {
      "epoch": 57,
      "train_loss": 1.0611271001398563,
      "test_loss": 1.8038644243240356,
      "train_acc": 70.44474283854167,
      "test_acc": 57.62,
      "lr": 0.6500970625342822,
      "mean_rho_t": 0.004282708207204839,
      "std_rho_t": 0.0037102936932913327,
      "mean_alpha_t": 0.001158117972784015,
      "mean_effective_wd": 6.444444444444444e-05,
      "total_wd_budget_epoch": 0.0029
    },
    {
      "epoch": 58,
      "train_loss": 1.0316029824316502,
      "test_loss": 1.847963463973999,
      "train_acc": 71.356201171875,
      "test_acc": 56.43,
      "lr": 0.6451628214611906,
      "mean_rho_t": 0.0035365462756649486,
      "std_rho_t": 0.0029049840596377797,
      "mean_alpha_t": 0.0010076947464024433,
      "mean_effective_wd": 6.444444444444444e-05,
      "total_wd_budget_epoch": 0.0029
    },
    {
      "epoch": 59,
      "train_loss": 1.0146054613093536,
      "test_loss": 1.8754309089660643,
      "train_acc": 71.61661783854167,
      "test_acc": 56.04,
      "lr": 0.6401680901303537,
      "mean_rho_t": 0.004238911336577444,
      "std_rho_t": 0.0036501004757172723,
      "mean_alpha_t": -0.001723351481528218,
      "mean_effective_wd": 6.444444444444444e-05,
      "total_wd_budget_epoch": 0.0029
    },
    {
      "epoch": 60,
      "train_loss": 1.0007710593442123,
      "test_loss": 1.8352208744049072,
      "train_acc": 72.17610677083333,
      "test_acc": 55.58,
      "lr": 0.6351141009169894,
      "mean_rho_t": 0.004063565593635752,
      "std_rho_t": 0.0034073768115293274,
      "mean_alpha_t": -0.009988860864758349,
      "mean_effective_wd": 6.444444444444444e-05,
      "total_wd_budget_epoch": 0.0029
    },
    {
      "epoch": 61,
      "train_loss": 0.9694116500516733,
      "test_loss": 1.7509046768188476,
      "train_acc": 72.930908203125,
      "test_acc": 58.01,
      "lr": 0.6300021008173116,
      "mean_rho_t": 0.004065584920233226,
      "std_rho_t": 0.003965047246858414,
      "mean_alpha_t": 0.007116270543730711,
      "mean_effective_wd": 6.444444444444444e-05,
      "total_wd_budget_epoch": 0.0029
    },
    {
      "epoch": 62,
      "train_loss": 0.9414590684076151,
      "test_loss": 1.8395663129806519,
      "train_acc": 73.77726236979167,
      "test_acc": 56.91,
      "lr": 0.6248333511408524,
      "mean_rho_t": 0.0037259460632356493,
      "std_rho_t": 0.003520496274489258,
      "mean_alpha_t": 0.003687125254852128,
      "mean_effective_wd": 6.444444444444444e-05,
      "total_wd_budget_epoch": 0.0029
    },
    {
      "epoch": 63,
      "train_loss": 0.9291608693699042,
      "test_loss": 1.723816733932495,
      "train_acc": 74.30623372395833,
      "test_acc": 58.8,
      "lr": 0.6196091271992528,
      "mean_rho_t": 0.004319831097365994,
      "std_rho_t": 0.003693387431446654,
      "mean_alpha_t": -4.3165257607244744e-05,
      "mean_effective_wd": 6.444444444444444e-05,
      "total_wd_budget_epoch": 0.0029
    },
    {
      "epoch": 64,
      "train_loss": 0.9060154979427656,
      "test_loss": 1.6864692293167114,
      "train_acc": 74.981689453125,
      "test_acc": 60.44,
      "lr": 0.6143307179915987,
      "mean_rho_t": 0.003889474699812709,
      "std_rho_t": 0.003436757982290342,
      "mean_alpha_t": -0.002317382999064692,
      "mean_effective_wd": 6.444444444444444e-05,
      "total_wd_budget_epoch": 0.0029
    },
    {
      "epoch": 65,
      "train_loss": 0.8944116942584515,
      "test_loss": 1.7112561725616455,
      "train_acc": 75.28279622395833,
      "test_acc": 60.4,
      "lr": 0.6089994258863796,
      "mean_rho_t": 0.004079455996761124,
      "std_rho_t": 0.0040170438380593984,
      "mean_alpha_t": 0.012254664664434336,
      "mean_effective_wd": 6.444444444444444e-05,
      "total_wd_budget_epoch": 0.0029
    },
    {
      "epoch": 66,
      "train_loss": 0.8628263026475906,
      "test_loss": 1.8114838607788086,
      "train_acc": 76.055908203125,
      "test_acc": 58.6,
      "lr": 0.6036165663001486,
      "mean_rho_t": 0.00359488356841813,
      "std_rho_t": 0.0032896496135213383,
      "mean_alpha_t": 0.008381345392893532,
      "mean_effective_wd": 6.444444444444444e-05,
      "total_wd_budget_epoch": 0.0029
    },
    {
      "epoch": 67,
      "train_loss": 0.8362875965734323,
      "test_loss": 1.8054233642578126,
      "train_acc": 76.89208984375,
      "test_acc": 58.69,
      "lr": 0.598183467372963,
      "mean_rho_t": 0.004328041692089488,
      "std_rho_t": 0.0038643632706690753,
      "mean_alpha_t": 0.0028439460403095317,
      "mean_effective_wd": 6.444444444444444e-05,
      "total_wd_budget_epoch": 0.0029
    },
    {
      "epoch": 68,
      "train_loss": 0.8160821298758189,
      "test_loss": 1.8748313247680664,
      "train_acc": 77.227783203125,
      "test_acc": 57.56,
      "lr": 0.5927014696406862,
      "mean_rho_t": 0.005609300327286634,
      "std_rho_t": 0.0031523201070933447,
      "mean_alpha_t": -0.007625507795087072,
      "mean_effective_wd": 6.444444444444444e-05,
      "total_wd_budget_epoch": 0.0029
    },
    {
      "epoch": 69,
      "train_loss": 0.9159963863591353,
      "test_loss": 1.8422053955078126,
      "train_acc": 74.97762044270833,
      "test_acc": 55.55,
      "lr": 0.5871719257042294,
      "mean_rho_t": 0.0038245749482557156,
      "std_rho_t": 0.003695955955299378,
      "mean_alpha_t": 0.00026339581052655596,
      "mean_effective_wd": 6.444444444444444e-05,
      "total_wd_budget_epoch": 0.0029
    },
    {
      "epoch": 70,
      "train_loss": 0.8622446122268835,
      "test_loss": 1.7543912700653077,
      "train_acc": 76.13525390625,
      "test_acc": 58.85,
      "lr": 0.5815961998958187,
      "mean_rho_t": 0.004005391461287317,
      "std_rho_t": 0.003353391265702649,
      "mean_alpha_t": -0.012676094948023995,
      "mean_effective_wd": 6.444444444444444e-05,
      "total_wd_budget_epoch": 0.0029
    },
    {
      "epoch": 71,
      "train_loss": 0.7980695875982443,
      "test_loss": 1.7304984380722046,
      "train_acc": 78.106689453125,
      "test_acc": 60.29,
      "lr": 0.575975667942366,
      "mean_rho_t": 0.0038106941694672504,
      "std_rho_t": 0.002951182423315504,
      "mean_alpha_t": -0.012212000260722942,
      "mean_effective_wd": 6.444444444444444e-05,
      "total_wd_budget_epoch": 0.0029
    },
    {
      "epoch": 72,
      "train_loss": 0.7637729234993458,
      "test_loss": 1.7432156227111817,
      "train_acc": 78.66617838541667,
      "test_acc": 59.6,
      "lr": 0.5703117166260291,
      "mean_rho_t": 0.0036698563477672963,
      "std_rho_t": 0.0032559618052150838,
      "mean_alpha_t": 0.013554665437897248,
      "mean_effective_wd": 6.444444444444444e-05,
      "total_wd_budget_epoch": 0.0029
    },
    {
      "epoch": 73,
      "train_loss": 0.7334107086062431,
      "test_loss": 1.711570181274414,
      "train_acc": 79.693603515625,
      "test_acc": 61.41,
      "lr": 0.5646057434420436,
      "mean_rho_t": 0.003768656364232026,
      "std_rho_t": 0.0031406397095487255,
      "mean_alpha_t": 0.0077694848039283615,
      "mean_effective_wd": 6.444444444444444e-05,
      "total_wd_budget_epoch": 0.0029
    },
    {
      "epoch": 74,
      "train_loss": 0.7156650486091772,
      "test_loss": 1.8419134901046752,
      "train_acc": 80.29581705729167,
      "test_acc": 59.52,
      "lr": 0.5588591562539122,
      "mean_rho_t": 0.003562440335348518,
      "std_rho_t": 0.0033946821231068763,
      "mean_alpha_t": -0.00027835355063414495,
      "mean_effective_wd": 6.444444444444444e-05,
      "total_wd_budget_epoch": 0.0029
    },
    {
      "epoch": 75,
      "train_loss": 0.7062067799270153,
      "test_loss": 1.7327665626525879,
      "train_acc": 80.70475260416667,
      "test_acc": 60.9,
      "lr": 0.553073372946036,
      "mean_rho_t": 0.003800500257159772,
      "std_rho_t": 0.0031154746131458306,
      "mean_alpha_t": 0.002959970146701086,
      "mean_effective_wd": 6.444444444444444e-05,
      "total_wd_budget_epoch": 0.0029
    },
    {
      "epoch": 76,
      "train_loss": 0.6862550067404906,
      "test_loss": 1.7845428342819214,
      "train_acc": 81.024169921875,
      "test_acc": 60.15,
      "lr": 0.5472498210738713,
      "mean_rho_t": 0.0039068197254242,
      "std_rho_t": 0.0029870634624397517,
      "mean_alpha_t": 0.007373934351769446,
      "mean_effective_wd": 6.444444444444444e-05,
      "total_wd_budget_epoch": 0.0029
    },
    {
      "epoch": 77,
      "train_loss": 0.6721891065438589,
      "test_loss": 1.7924488807678223,
      "train_acc": 81.561279296875,
      "test_acc": 60.71,
      "lr": 0.541389937511703,
      "mean_rho_t": 0.0038287620493262144,
      "std_rho_t": 0.003189944884232083,
      "mean_alpha_t": 0.00574644786394339,
      "mean_effective_wd": 6.444444444444444e-05,
      "total_wd_budget_epoch": 0.0029
    },
    {
      "epoch": 78,
      "train_loss": 0.6723426406582197,
      "test_loss": 1.7560387300491334,
      "train_acc": 81.35172526041667,
      "test_acc": 61.71,
      "lr": 0.5354951680981167,
      "mean_rho_t": 0.004216330948131271,
      "std_rho_t": 0.003639967902725211,
      "mean_alpha_t": 0.0017523710974812411,
      "mean_effective_wd": 6.444444444444444e-05,
      "total_wd_budget_epoch": 0.0029
    },
    {
      "epoch": 79,
      "train_loss": 0.6395039943357309,
      "test_loss": 1.7479658414840697,
      "train_acc": 82.46663411458333,
      "test_acc": 61.38,
      "lr": 0.5295669672792598,
      "mean_rho_t": 0.003666227693076716,
      "std_rho_t": 0.0030024405490869893,
      "mean_alpha_t": 0.007943671326439111,
      "mean_effective_wd": 6.444444444444444e-05,
      "total_wd_budget_epoch": 0.0029
    },
    {
      "epoch": 80,
      "train_loss": 0.6179963399966558,
      "test_loss": 1.736293190765381,
      "train_acc": 83.050537109375,
      "test_acc": 62.54,
      "lr": 0.523606797749979,
      "mean_rho_t": 0.0037343809042843764,
      "std_rho_t": 0.0027259649932806287,
      "mean_alpha_t": 0.006873642307041303,
      "mean_effective_wd": 6.444444444444444e-05,
      "total_wd_budget_epoch": 0.0029
    },
    {
      "epoch": 81,
      "train_loss": 0.6184268581370512,
      "test_loss": 1.8216018934249878,
      "train_acc": 83.10546875,
      "test_acc": 60.5,
      "lr": 0.5176161300929216,
      "mean_rho_t": 0.003857031290293117,
      "std_rho_t": 0.002920315446355424,
      "mean_alpha_t": 0.01267837219599208,
      "mean_effective_wd": 6.444444444444444e-05,
      "total_wd_budget_epoch": 0.0029
    },
    {
      "epoch": 82,
      "train_loss": 0.6221613027155399,
      "test_loss": 1.8291070425033569,
      "train_acc": 82.977294921875,
      "test_acc": 61.07,
      "lr": 0.5115964424156918,
      "mean_rho_t": 0.0037223032771498267,
      "std_rho_t": 0.0027956533068632466,
      "mean_alpha_t": 0.005471567315731863,
      "mean_effective_wd": 6.444444444444444e-05,
      "total_wd_budget_epoch": 0.0029
    },
    {
      "epoch": 83,
      "train_loss": 0.5875173397362232,
      "test_loss": 1.725134790611267,
      "train_acc": 83.91316731770833,
      "test_acc": 61.74,
      "lr": 0.5055492199861491,
      "mean_rho_t": 0.0034660839126546194,
      "std_rho_t": 0.0031150800211163765,
      "mean_alpha_t": 0.0034832213933342704,
      "mean_effective_wd": 6.444444444444444e-05,
      "total_wd_budget_epoch": 0.0029
    },
    {
      "epoch": 84,
      "train_loss": 0.5640875156968832,
      "test_loss": 1.7409725509643554,
      "train_acc": 84.46248372395833,
      "test_acc": 62.16,
      "lr": 0.4994759548659419,
      "mean_rho_t": 0.0036061252130963166,
      "std_rho_t": 0.002708018299265383,
      "mean_alpha_t": 7.780973271650317e-05,
      "mean_effective_wd": 6.444444444444444e-05,
      "total_wd_budget_epoch": 0.0029
    },
    {
      "epoch": 85,
      "train_loss": 0.5435917718956867,
      "test_loss": 1.7153041704177856,
      "train_acc": 85.06876627604167,
      "test_acc": 63.07,
      "lr": 0.49337814554236226,
      "mean_rho_t": 0.0035080829790512455,
      "std_rho_t": 0.0028445944047626502,
      "mean_alpha_t": 0.006398777260179749,
      "mean_effective_wd": 6.444444444444444e-05,
      "total_wd_budget_epoch": 0.0029
    },
    {
      "epoch": 86,
      "train_loss": 0.5274962646265825,
      "test_loss": 1.7242375993728638,
      "train_acc": 85.56111653645833,
      "test_acc": 62.88,
      "lr": 0.4872572965586171,
      "mean_rho_t": 0.003271838015027522,
      "std_rho_t": 0.0024952238782961957,
      "mean_alpha_t": -0.000718761142277922,
      "mean_effective_wd": 6.444444444444444e-05,
      "total_wd_budget_epoch": 0.0029
    },
    {
      "epoch": 87,
      "train_loss": 0.5177664253860712,
      "test_loss": 1.6628349710464478,
      "train_acc": 85.79305013020833,
      "test_acc": 63.31,
      "lr": 0.4811149181426051,
      "mean_rho_t": 0.0034185405204694747,
      "std_rho_t": 0.0024750306697924477,
      "mean_alpha_t": -0.006133257678969737,
      "mean_effective_wd": 6.444444444444444e-05,
      "total_wd_budget_epoch": 0.0029
    },
    {
      "epoch": 88,
      "train_loss": 0.5042192557205757,
      "test_loss": 1.7469022951126099,
      "train_acc": 86.16129557291667,
      "test_acc": 63.38,
      "lr": 0.47495252583428993,
      "mean_rho_t": 0.00338069672203575,
      "std_rho_t": 0.0024850811192071998,
      "mean_alpha_t": -0.004354109844322819,
      "mean_effective_wd": 6.444444444444444e-05,
      "total_wd_budget_epoch": 0.0029
    },
    {
      "epoch": 89,
      "train_loss": 0.47134165341655415,
      "test_loss": 1.741347952079773,
      "train_acc": 87.15006510416667,
      "test_acc": 63.11,
      "lr": 0.4687716401117638,
      "mean_rho_t": 0.0031991249832462754,
      "std_rho_t": 0.002761817200348083,
      "mean_alpha_t": 0.0019134123956447147,
      "mean_effective_wd": 6.444444444444444e-05,
      "total_wd_budget_epoch": 0.0029
    },
    {
      "epoch": 90,
      "train_loss": 0.4595114625990391,
      "test_loss": 1.7434533603668212,
      "train_acc": 87.47762044270833,
      "test_acc": 63.86,
      "lr": 0.4625737860160924,
      "mean_rho_t": 0.003137877689994026,
      "std_rho_t": 0.0024625315500191106,
      "mean_alpha_t": 0.0007189866300138128,
      "mean_effective_wd": 6.444444444444444e-05,
      "total_wd_budget_epoch": 0.0029
    },
    {
      "epoch": 91,
      "train_loss": 0.4614753356824319,
      "test_loss": 1.7554063859939575,
      "train_acc": 87.30875651041667,
      "test_acc": 63.13,
      "lr": 0.45636049277503316,
      "mean_rho_t": 0.0035288902870832927,
      "std_rho_t": 0.002424422763127363,
      "mean_alpha_t": 0.00136863884066676,
      "mean_effective_wd": 6.444444444444444e-05,
      "total_wd_budget_epoch": 0.0029
    },
    {
      "epoch": 92,
      "train_loss": 0.4421401632328828,
      "test_loss": 1.8198393306732177,
      "train_acc": 87.75431315104167,
      "test_acc": 62.56,
      "lr": 0.45013329342572184,
      "mean_rho_t": 0.003347587621185746,
      "std_rho_t": 0.0025926923251405783,
      "mean_alpha_t": -0.0005221722250734978,
      "mean_effective_wd": 6.444444444444444e-05,
      "total_wd_budget_epoch": 0.0029
    },
    {
      "epoch": 93,
      "train_loss": 0.4327377049873273,
      "test_loss": 1.751502123451233,
      "train_acc": 88.275146484375,
      "test_acc": 63.55,
      "lr": 0.44389372443641817,
      "mean_rho_t": 0.0028491938134301313,
      "std_rho_t": 0.002300283552083104,
      "mean_alpha_t": 0.0003296265000094849,
      "mean_effective_wd": 6.444444444444444e-05,
      "total_wd_budget_epoch": 0.0029
    },
    {
      "epoch": 94,
      "train_loss": 0.41201502953966457,
      "test_loss": 1.8367017250061035,
      "train_acc": 88.72477213541667,
      "test_acc": 62.88,
      "lr": 0.43764332532740574,
      "mean_rho_t": 0.0032831161875416606,
      "std_rho_t": 0.002507990861870678,
      "mean_alpha_t": 0.007250713155076126,
      "mean_effective_wd": 6.444444444444444e-05,
      "total_wd_budget_epoch": 0.0029
    },
    {
      "epoch": 95,
      "train_loss": 0.40184980382521945,
      "test_loss": 1.8258392105102539,
      "train_acc": 88.94246419270833,
      "test_acc": 62.94,
      "lr": 0.431383638291138,
      "mean_rho_t": 0.00342159144843962,
      "std_rho_t": 0.0027496630496642365,
      "mean_alpha_t": -0.006354404436201665,
      "mean_effective_wd": 6.444444444444444e-05,
      "total_wd_budget_epoch": 0.0029
    },
    {
      "epoch": 96,
      "train_loss": 0.38475710650285083,
      "test_loss": 1.8125606369018554,
      "train_acc": 89.453125,
      "test_acc": 64.04,
      "lr": 0.42511620781172543,
      "mean_rho_t": 0.003534056903856681,
      "std_rho_t": 0.002534867410612674,
      "mean_alpha_t": -0.005402236252417975,
      "mean_effective_wd": 6.444444444444444e-05,
      "total_wd_budget_epoch": 0.0029
    },
    {
      "epoch": 97,
      "train_loss": 0.3846027906984091,
      "test_loss": 1.8899662828445434,
      "train_acc": 89.39005533854167,
      "test_acc": 63.25,
      "lr": 0.41884258028385707,
      "mean_rho_t": 0.0031538977408271606,
      "std_rho_t": 0.0025036804687827733,
      "mean_alpha_t": -0.013104610344184118,
      "mean_effective_wd": 6.444444444444444e-05,
      "total_wd_budget_epoch": 0.0029
    },
    {
      "epoch": 98,
      "train_loss": 0.37533126398921013,
      "test_loss": 1.8737075239181518,
      "train_acc": 89.9658203125,
      "test_acc": 62.67,
      "lr": 0.41256430363125135,
      "mean_rho_t": 0.0034097384373721357,
      "std_rho_t": 0.0024464678313315673,
      "mean_alpha_t": 0.0029965922141567433,
      "mean_effective_wd": 6.444444444444444e-05,
      "total_wd_budget_epoch": 0.0029
    },
    {
      "epoch": 99,
      "train_loss": 0.35714887517193955,
      "test_loss": 1.8506744464874267,
      "train_acc": 90.22216796875,
      "test_acc": 64.14,
      "lr": 0.40628292692472834,
      "mean_rho_t": 0.00319402806129691,
      "std_rho_t": 0.002438132661809682,
      "mean_alpha_t": -0.0008410958114807784,
      "mean_effective_wd": 6.444444444444444e-05,
      "total_wd_budget_epoch": 0.0029
    },
    {
      "epoch": 100,
      "train_loss": 0.3580094886322816,
      "test_loss": 1.8191421392440796,
      "train_acc": 90.23234049479167,
      "test_acc": 63.24,
      "lr": 0.4,
      "mean_rho_t": 0.0028578611933962913,
      "std_rho_t": 0.002648680466844934,
      "mean_alpha_t": 0.0020980589899463205,
      "mean_effective_wd": 6.444444444444444e-05,
      "total_wd_budget_epoch": 0.0029
    },
    {
      "epoch": 101,
      "train_loss": 0.35361374852557975,
      "test_loss": 1.8066191621780396,
      "train_acc": 90.38492838541667,
      "test_acc": 63.97,
      "lr": 0.3937170730752718,
      "mean_rho_t": 0.00303638448453873,
      "std_rho_t": 0.002399927567943843,
      "mean_alpha_t": 0.0003232127314414252,
      "mean_effective_wd": 6.444444444444444e-05,
      "total_wd_budget_epoch": 0.0029
    },
    {
      "epoch": 102,
      "train_loss": 0.3338735395421584,
      "test_loss": 1.8296229949951173,
      "train_acc": 90.92610677083333,
      "test_acc": 64.29,
      "lr": 0.3874356963687487,
      "mean_rho_t": 0.0029084647717651777,
      "std_rho_t": 0.00225342038055944,
      "mean_alpha_t": -0.007450988767734634,
      "mean_effective_wd": 6.444444444444444e-05,
      "total_wd_budget_epoch": 0.0029
    },
    {
      "epoch": 103,
      "train_loss": 0.32074555351088446,
      "test_loss": 1.875672548675537,
      "train_acc": 91.30045572916667,
      "test_acc": 64.21,
      "lr": 0.381157419716143,
      "mean_rho_t": 0.0029501191886941933,
      "std_rho_t": 0.0021395670819545276,
      "mean_alpha_t": 0.0027392140654168362,
      "mean_effective_wd": 6.444444444444444e-05,
      "total_wd_budget_epoch": 0.0029
    },
    {
      "epoch": 104,
      "train_loss": 0.29813199241956073,
      "test_loss": 1.8852901359558105,
      "train_acc": 91.87215169270833,
      "test_acc": 64.19,
      "lr": 0.37488379218827467,
      "mean_rho_t": 0.002818196907637811,
      "std_rho_t": 0.0020259964030895665,
      "mean_alpha_t": -0.004141000384997146,
      "mean_effective_wd": 6.444444444444444e-05,
      "total_wd_budget_epoch": 0.0029
    },
    {
      "epoch": 105,
      "train_loss": 0.29852744440237683,
      "test_loss": 1.8597225173950196,
      "train_acc": 91.93115234375,
      "test_acc": 64.67,
      "lr": 0.3686163617088621,
      "mean_rho_t": 0.0030756064197008204,
      "std_rho_t": 0.002082322650903602,
      "mean_alpha_t": -0.0028923853259281373,
      "mean_effective_wd": 6.444444444444444e-05,
      "total_wd_budget_epoch": 0.0029
    },
    {
      "epoch": 106,
      "train_loss": 0.2947313617914915,
      "test_loss": 1.8797392360687255,
      "train_acc": 91.93929036458333,
      "test_acc": 64.88,
      "lr": 0.3623566746725943,
      "mean_rho_t": 0.0033451745268436813,
      "std_rho_t": 0.0020296428514109464,
      "mean_alpha_t": 0.002595456604922407,
      "mean_effective_wd": 6.444444444444444e-05,
      "total_wd_budget_epoch": 0.0029
    },
    {
      "epoch": 107,
      "train_loss": 0.2790847945337494,
      "test_loss": 1.868309358215332,
      "train_acc": 92.42960611979167,
      "test_acc": 64.78,
      "lr": 0.35610627556358193,
      "mean_rho_t": 0.0030702402601806627,
      "std_rho_t": 0.0021916158196722095,
      "mean_alpha_t": -0.009907302201429583,
      "mean_effective_wd": 6.444444444444444e-05,
      "total_wd_budget_epoch": 0.0029
    },
    {
      "epoch": 108,
      "train_loss": 0.265824628683428,
      "test_loss": 1.8678375463485717,
      "train_acc": 92.75105794270833,
      "test_acc": 64.9,
      "lr": 0.3498667065742784,
      "mean_rho_t": 0.003425304678928034,
      "std_rho_t": 0.0025434471177017445,
      "mean_alpha_t": -0.008825789075235136,
      "mean_effective_wd": 6.444444444444444e-05,
      "total_wd_budget_epoch": 0.0029
    },
    {
      "epoch": 109,
      "train_loss": 0.25380306753019494,
      "test_loss": 1.8542438201904297,
      "train_acc": 92.999267578125,
      "test_acc": 65.7,
      "lr": 0.34363950722496706,
      "mean_rho_t": 0.0025665264717628896,
      "std_rho_t": 0.0017584826988189918,
      "mean_alpha_t": -0.006363486950413383,
      "mean_effective_wd": 6.444444444444444e-05,
      "total_wd_budget_epoch": 0.0029
    },
    {
      "epoch": 110,
      "train_loss": 0.24763024846712747,
      "test_loss": 1.9028274061203003,
      "train_acc": 93.27799479166667,
      "test_acc": 65.38,
      "lr": 0.3374262139839077,
      "mean_rho_t": 0.003423309559504275,
      "std_rho_t": 0.002369082769681757,
      "mean_alpha_t": -0.0038340824166432554,
      "mean_effective_wd": 6.444444444444444e-05,
      "total_wd_budget_epoch": 0.0029
    },
    {
      "epoch": 111,
      "train_loss": 0.23921731455872455,
      "test_loss": 1.978749644088745,
      "train_acc": 93.487548828125,
      "test_acc": 65.0,
      "lr": 0.3312283598882362,
      "mean_rho_t": 0.0026501898636459038,
      "std_rho_t": 0.0017045050975089738,
      "mean_alpha_t": -0.0022531263772189603,
      "mean_effective_wd": 6.444444444444444e-05,
      "total_wd_budget_epoch": 0.0029
    },
    {
      "epoch": 112,
      "train_loss": 0.23111280364294848,
      "test_loss": 1.9290444972991942,
      "train_acc": 93.75,
      "test_acc": 65.41,
      "lr": 0.32504747416571017,
      "mean_rho_t": 0.002824943768399512,
      "std_rho_t": 0.0017942401820206315,
      "mean_alpha_t": -0.005481718349854963,
      "mean_effective_wd": 6.444444444444444e-05,
      "total_wd_budget_epoch": 0.0029
    },
    {
      "epoch": 113,
      "train_loss": 0.2194269485771656,
      "test_loss": 1.9169731702804564,
      "train_acc": 94.17317708333333,
      "test_acc": 65.72,
      "lr": 0.31888508185739506,
      "mean_rho_t": 0.0029527242156144867,
      "std_rho_t": 0.002152948225344175,
      "mean_alpha_t": 0.00644009824224369,
      "mean_effective_wd": 6.444444444444444e-05,
      "total_wd_budget_epoch": 0.0029
    },
    {
      "epoch": 114,
      "train_loss": 0.2256916326781114,
      "test_loss": 1.9373573738098144,
      "train_acc": 93.88631184895833,
      "test_acc": 64.88,
      "lr": 0.3127427034413831,
      "mean_rho_t": 0.0030912776914123123,
      "std_rho_t": 0.002102620125515154,
      "mean_alpha_t": 0.0064651853862851055,
      "mean_effective_wd": 6.444444444444444e-05,
      "total_wd_budget_epoch": 0.0029
    },
    {
      "epoch": 115,
      "train_loss": 0.21394229711343846,
      "test_loss": 1.9473676069259644,
      "train_acc": 94.097900390625,
      "test_acc": 65.2,
      "lr": 0.3066218544576378,
      "mean_rho_t": 0.0032707724139229917,
      "std_rho_t": 0.002186859706846417,
      "mean_alpha_t": -0.0042417335161773805,
      "mean_effective_wd": 6.444444444444444e-05,
      "total_wd_budget_epoch": 0.0029
    },
    {
      "epoch": 116,
      "train_loss": 0.1911946147059401,
      "test_loss": 1.9267696401596068,
      "train_acc": 94.75504557291667,
      "test_acc": 66.06,
      "lr": 0.30052404513405806,
      "mean_rho_t": 0.002525038794885813,
      "std_rho_t": 0.0016835902765915524,
      "mean_alpha_t": 0.003103505463390709,
      "mean_effective_wd": 6.444444444444444e-05,
      "total_wd_budget_epoch": 0.0029
    },
    {
      "epoch": 117,
      "train_loss": 0.18568745317558447,
      "test_loss": 1.9660302394866944,
      "train_acc": 94.93815104166667,
      "test_acc": 65.63,
      "lr": 0.2944507800138509,
      "mean_rho_t": 0.0025057391783901433,
      "std_rho_t": 0.0015509959423461687,
      "mean_alpha_t": -0.005038096607771069,
      "mean_effective_wd": 6.444444444444444e-05,
      "total_wd_budget_epoch": 0.0029
    },
    {
      "epoch": 118,
      "train_loss": 0.1970250696564714,
      "test_loss": 2.002410021018982,
      "train_acc": 94.80387369791667,
      "test_acc": 65.31,
      "lr": 0.28840355758430836,
      "mean_rho_t": 0.0024365236137665683,
      "std_rho_t": 0.0017351565425704836,
      "mean_alpha_t": 0.0012625101203826569,
      "mean_effective_wd": 6.444444444444444e-05,
      "total_wd_budget_epoch": 0.0029
    },
    {
      "epoch": 119,
      "train_loss": 0.19514995937546095,
      "test_loss": 1.9621907024383545,
      "train_acc": 94.74283854166667,
      "test_acc": 65.29,
      "lr": 0.2823838699070785,
      "mean_rho_t": 0.002374633591952516,
      "std_rho_t": 0.0015567436289746772,
      "mean_alpha_t": -0.004593415294875568,
      "mean_effective_wd": 6.444444444444444e-05,
      "total_wd_budget_epoch": 0.0029
    },
    {
      "epoch": 120,
      "train_loss": 0.17716570540020862,
      "test_loss": 1.990951341819763,
      "train_acc": 95.21484375,
      "test_acc": 65.99,
      "lr": 0.2763932022500212,
      "mean_rho_t": 0.002724942553253046,
      "std_rho_t": 0.0016166819347670208,
      "mean_alpha_t": 0.0029785554681109375,
      "mean_effective_wd": 6.444444444444444e-05,
      "total_wd_budget_epoch": 0.0029
    },
    {
      "epoch": 121,
      "train_loss": 0.1674425721478959,
      "test_loss": 2.0052622535705567,
      "train_acc": 95.49153645833333,
      "test_acc": 66.05,
      "lr": 0.2704330327207402,
      "mean_rho_t": 0.0021749598057045475,
      "std_rho_t": 0.001350352430653701,
      "mean_alpha_t": -0.0014175531661946047,
      "mean_effective_wd": 6.444444444444444e-05,
      "total_wd_budget_epoch": 0.0029
    },
    {
      "epoch": 122,
      "train_loss": 0.15560500401382646,
      "test_loss": 2.024456258392334,
      "train_acc": 95.7275390625,
      "test_acc": 65.73,
      "lr": 0.26450483190188345,
      "mean_rho_t": 0.003028344006701885,
      "std_rho_t": 0.0015828753578956904,
      "mean_alpha_t": 0.007106735594638527,
      "mean_effective_wd": 6.444444444444444e-05,
      "total_wd_budget_epoch": 0.0029
    },
    {
      "epoch": 123,
      "train_loss": 0.15824021476631364,
      "test_loss": 2.0051444679260255,
      "train_acc": 95.71736653645833,
      "test_acc": 66.11,
      "lr": 0.2586100624882972,
      "mean_rho_t": 0.002698802155268001,
      "std_rho_t": 0.0015459204463918953,
      "mean_alpha_t": 0.004911351286217718,
      "mean_effective_wd": 6.444444444444444e-05,
      "total_wd_budget_epoch": 0.0029
    },
    {
      "epoch": 124,
      "train_loss": 0.14599950394282737,
      "test_loss": 2.0290839262008666,
      "train_acc": 96.05305989583333,
      "test_acc": 66.34,
      "lr": 0.25275017892612894,
      "mean_rho_t": 0.0024004952096941014,
      "std_rho_t": 0.0015825929603408074,
      "mean_alpha_t": -0.004682757083038128,
      "mean_effective_wd": 6.444444444444444e-05,
      "total_wd_budget_epoch": 0.0029
    },
    {
      "epoch": 125,
      "train_loss": 0.13532833941280842,
      "test_loss": 2.0734300277709963,
      "train_acc": 96.3134765625,
      "test_acc": 66.34,
      "lr": 0.2469266270539642,
      "mean_rho_t": 0.002689843774081024,
      "std_rho_t": 0.0016955875414469915,
      "mean_alpha_t": 0.00612690709707576,
      "mean_effective_wd": 6.444444444444444e-05,
      "total_wd_budget_epoch": 0.0029
    },
    {
      "epoch": 126,
      "train_loss": 0.13234016501034299,
      "test_loss": 1.9839544065475463,
      "train_acc": 96.478271484375,
      "test_acc": 66.28,
      "lr": 0.2411408437460877,
      "mean_rho_t": 0.0020714313183404134,
      "std_rho_t": 0.0011954051884833891,
      "mean_alpha_t": -0.005304249672692657,
      "mean_effective_wd": 6.444444444444444e-05,
      "total_wd_budget_epoch": 0.0029
    },
    {
      "epoch": 127,
      "train_loss": 0.1316991544639071,
      "test_loss": 2.108282588195801,
      "train_acc": 96.490478515625,
      "test_acc": 65.77,
      "lr": 0.2353942565579565,
      "mean_rho_t": 0.0024476722559240945,
      "std_rho_t": 0.0015256509858950485,
      "mean_alpha_t": 0.003098669497993154,
      "mean_effective_wd": 6.444444444444444e-05,
      "total_wd_budget_epoch": 0.0029
    },
    {
      "epoch": 128,
      "train_loss": 0.12337129035343726,
      "test_loss": 2.0003304349899294,
      "train_acc": 96.649169921875,
      "test_acc": 66.68,
      "lr": 0.22968828337397096,
      "mean_rho_t": 0.0027946413829661176,
      "std_rho_t": 0.0016518148607294328,
      "mean_alpha_t": 0.007536011303625505,
      "mean_effective_wd": 6.444444444444444e-05,
      "total_wd_budget_epoch": 0.0029
    },
    {
      "epoch": 129,
      "train_loss": 0.11564508142570655,
      "test_loss": 2.047061776161194,
      "train_acc": 96.82820638020833,
      "test_acc": 66.99,
      "lr": 0.22402433205763395,
      "mean_rho_t": 0.0025125496625259276,
      "std_rho_t": 0.001347378800702459,
      "mean_alpha_t": 0.00500760921642202,
      "mean_effective_wd": 6.444444444444444e-05,
      "total_wd_budget_epoch": 0.0029
    },
    {
      "epoch": 130,
      "train_loss": 0.10863453584412734,
      "test_loss": 2.066896181678772,
      "train_acc": 97.09676106770833,
      "test_acc": 67.02,
      "lr": 0.2184038001041813,
      "mean_rho_t": 0.0021175298922226984,
      "std_rho_t": 0.0013605382536936487,
      "mean_alpha_t": -0.005597122158582009,
      "mean_effective_wd": 6.444444444444444e-05,
      "total_wd_budget_epoch": 0.0029
    },
    {
      "epoch": 131,
      "train_loss": 0.10371366833957534,
      "test_loss": 2.0849718172073364,
      "train_acc": 97.198486328125,
      "test_acc": 66.64,
      "lr": 0.21282807429577072,
      "mean_rho_t": 0.0020275125679000473,
      "std_rho_t": 0.001180003322727713,
      "mean_alpha_t": -0.005630447204478937,
      "mean_effective_wd": 6.444444444444444e-05,
      "total_wd_budget_epoch": 0.0029
    },
    {
      "epoch": 132,
      "train_loss": 0.1018965143399934,
      "test_loss": 2.111022576904297,
      "train_acc": 97.29207356770833,
      "test_acc": 66.32,
      "lr": 0.20729853035931384,
      "mean_rho_t": 0.0024240423265352194,
      "std_rho_t": 0.0012760227962553326,
      "mean_alpha_t": 0.0009053287705060075,
      "mean_effective_wd": 6.444444444444444e-05,
      "total_wd_budget_epoch": 0.0029
    },
    {
      "epoch": 133,
      "train_loss": 0.09110146784223616,
      "test_loss": 2.1131908988952635,
      "train_acc": 97.56673177083333,
      "test_acc": 66.85,
      "lr": 0.20181653262703697,
      "mean_rho_t": 0.002000687716530206,
      "std_rho_t": 0.0011104744004266829,
      "mean_alpha_t": -0.0054467203364446685,
      "mean_effective_wd": 6.444444444444444e-05,
      "total_wd_budget_epoch": 0.0029
    },
    {
      "epoch": 134,
      "train_loss": 0.08142282674089074,
      "test_loss": 2.188374125289917,
      "train_acc": 97.76407877604167,
      "test_acc": 67.29,
      "lr": 0.19638343369985148,
      "mean_rho_t": 0.0023722246193643884,
      "std_rho_t": 0.00134797220195055,
      "mean_alpha_t": 0.005942823289050304,
      "mean_effective_wd": 6.444444444444444e-05,
      "total_wd_budget_epoch": 0.0029
    },
    {
      "epoch": 135,
      "train_loss": 0.08690390021850665,
      "test_loss": 2.173180340194702,
      "train_acc": 97.69287109375,
      "test_acc": 66.8,
      "lr": 0.19100057411362048,
      "mean_rho_t": 0.002598488178580159,
      "std_rho_t": 0.001500980970044305,
      "mean_alpha_t": 0.012953480679822884,
      "mean_effective_wd": 6.444444444444444e-05,
      "total_wd_budget_epoch": 0.0029
    },
    {
      "epoch": 136,
      "train_loss": 0.08869222737848759,
      "test_loss": 2.132009546279907,
      "train_acc": 97.59724934895833,
      "test_acc": 67.05,
      "lr": 0.18566928200840127,
      "mean_rho_t": 0.00238985866723878,
      "std_rho_t": 0.0012466002939267946,
      "mean_alpha_t": -0.008200253013147992,
      "mean_effective_wd": 6.444444444444444e-05,
      "total_wd_budget_epoch": 0.0029
    },
    {
      "epoch": 137,
      "train_loss": 0.08688800145561497,
      "test_loss": 2.12857629776001,
      "train_acc": 97.68473307291667,
      "test_acc": 67.22,
      "lr": 0.18039087280074725,
      "mean_rho_t": 0.002276588512330357,
      "std_rho_t": 0.0012248185182161858,
      "mean_alpha_t": -0.0073147723457327694,
      "mean_effective_wd": 6.444444444444444e-05,
      "total_wd_budget_epoch": 0.0029
    },
    {
      "epoch": 138,
      "train_loss": 0.07556088827550411,
      "test_loss": 2.144016990661621,
      "train_acc": 97.97159830729167,
      "test_acc": 67.3,
      "lr": 0.17516664885914773,
      "mean_rho_t": 0.0018515728835616255,
      "std_rho_t": 0.0011583922005771999,
      "mean_alpha_t": -0.001199023830824777,
      "mean_effective_wd": 6.444444444444444e-05,
      "total_wd_budget_epoch": 0.0029
    },
    {
      "epoch": 139,
      "train_loss": 0.07336004885534446,
      "test_loss": 2.160635561180115,
      "train_acc": 98.040771484375,
      "test_acc": 66.78,
      "lr": 0.1699978991826886,
      "mean_rho_t": 0.0025466317020467243,
      "std_rho_t": 0.001353936908944457,
      "mean_alpha_t": -0.0011573831906331474,
      "mean_effective_wd": 6.444444444444444e-05,
      "total_wd_budget_epoch": 0.0029
    },
    {
      "epoch": 140,
      "train_loss": 0.07234293362125754,
      "test_loss": 2.127666602897644,
      "train_acc": 98.046875,
      "test_acc": 67.77,
      "lr": 0.1648858990830108,
      "mean_rho_t": 0.001805795876435301,
      "std_rho_t": 0.0011073578962236055,
      "mean_alpha_t": 0.005845192558833066,
      "mean_effective_wd": 6.444444444444444e-05,
      "total_wd_budget_epoch": 0.0029
    },
    {
      "epoch": 141,
      "train_loss": 0.06940669985488057,
      "test_loss": 2.1706843587875366,
      "train_acc": 98.15470377604167,
      "test_acc": 67.57,
      "lr": 0.15983190986964646,
      "mean_rho_t": 0.002100794853339898,
      "std_rho_t": 0.0011390886194500537,
      "mean_alpha_t": 6.064884922438837e-05,
      "mean_effective_wd": 6.444444444444444e-05,
      "total_wd_budget_epoch": 0.0029
    },
    {
      "epoch": 142,
      "train_loss": 0.06441211599546175,
      "test_loss": 2.2095552307128905,
      "train_acc": 98.26456705729167,
      "test_acc": 67.4,
      "lr": 0.15483717853880938,
      "mean_rho_t": 0.001966511488413623,
      "std_rho_t": 0.0010434159834076125,
      "mean_alpha_t": -0.004157937160852996,
      "mean_effective_wd": 6.444444444444444e-05,
      "total_wd_budget_epoch": 0.0029
    },
    {
      "epoch": 143,
      "train_loss": 0.05673984112218022,
      "test_loss": 2.2628348834991456,
      "train_acc": 98.50056966145833,
      "test_acc": 67.63,
      "lr": 0.14990293746571792,
      "mean_rho_t": 0.0021655172036076542,
      "std_rho_t": 0.0012003631418236978,
      "mean_alpha_t": 0.0015103491016934434,
      "mean_effective_wd": 6.444444444444444e-05,
      "total_wd_budget_epoch": 0.0029
    },
    {
      "epoch": 144,
      "train_loss": 0.05346892479186257,
      "test_loss": 2.2887734771728514,
      "train_acc": 98.58194986979167,
      "test_acc": 67.29,
      "lr": 0.14503040410052412,
      "mean_rho_t": 0.0019865427778329903,
      "std_rho_t": 0.0009828470078107078,
      "mean_alpha_t": -0.0033226816658535854,
      "mean_effective_wd": 6.444444444444444e-05,
      "total_wd_budget_epoch": 0.0029
    },
    {
      "epoch": 145,
      "train_loss": 0.05508655868470669,
      "test_loss": 2.268803997039795,
      "train_acc": 98.50260416666667,
      "test_acc": 67.38,
      "lr": 0.1402207806679266,
      "mean_rho_t": 0.001857172731528606,
      "std_rho_t": 0.0010227155457798768,
      "mean_alpha_t": 0.00220189236034053,
      "mean_effective_wd": 6.444444444444444e-05,
      "total_wd_budget_epoch": 0.0029
    },
    {
      "epoch": 146,
      "train_loss": 0.05102014921916028,
      "test_loss": 2.2454946235656736,
      "train_acc": 98.663330078125,
      "test_acc": 67.71,
      "lr": 0.13547525387053932,
      "mean_rho_t": 0.001706903806584935,
      "std_rho_t": 0.0010330341963643646,
      "mean_alpha_t": -0.0027828189037358976,
      "mean_effective_wd": 6.444444444444444e-05,
      "total_wd_budget_epoch": 0.0029
    },
    {
      "epoch": 147,
      "train_loss": 0.049782679261018835,
      "test_loss": 2.300243560409546,
      "train_acc": 98.72639973958333,
      "test_acc": 67.64,
      "lr": 0.13079499459609065,
      "mean_rho_t": 0.0022781215696573136,
      "std_rho_t": 0.0012037317357450345,
      "mean_alpha_t": 0.005163132620919778,
      "mean_effective_wd": 6.444444444444444e-05,
      "total_wd_budget_epoch": 0.0029
    },
    {
      "epoch": 148,
      "train_loss": 0.04850717591277013,
      "test_loss": 2.2771395904541016,
      "train_acc": 98.663330078125,
      "test_acc": 67.86,
      "lr": 0.12618115762852453,
      "mean_rho_t": 0.0021272726337734867,
      "std_rho_t": 0.0010870611666114849,
      "mean_alpha_t": -0.0020914736431693936,
      "mean_effective_wd": 6.444444444444444e-05,
      "total_wd_budget_epoch": 0.0029
    },
    {
      "epoch": 149,
      "train_loss": 0.04192770062945783,
      "test_loss": 2.2725394218444825,
      "train_acc": 98.86881510416667,
      "test_acc": 68.1,
      "lr": 0.12163488136307428,
      "mean_rho_t": 0.0020730909060157534,
      "std_rho_t": 0.0010037675939113498,
      "mean_alpha_t": -0.00676927144251463,
      "mean_effective_wd": 6.444444444444444e-05,
      "total_wd_budget_epoch": 0.0029
    },
    {
      "epoch": 150,
      "train_loss": 0.042660666590866946,
      "test_loss": 2.310110567474365,
      "train_acc": 98.870849609375,
      "test_acc": 67.82,
      "lr": 0.11715728752538102,
      "mean_rho_t": 0.001778458023947742,
      "std_rho_t": 0.0009203412179414909,
      "mean_alpha_t": 0.012679564548085522,
      "mean_effective_wd": 6.444444444444444e-05,
      "total_wd_budget_epoch": 0.0029
    },
    {
      "epoch": 151,
      "train_loss": 0.03852665525240203,
      "test_loss": 2.3405598205566407,
      "train_acc": 99.01326497395833,
      "test_acc": 68.15,
      "lr": 0.11274948089472453,
      "mean_rho_t": 0.0011755965158989818,
      "std_rho_t": 0.0009439093466558519,
      "mean_alpha_t": -0.004694026011772623,
      "mean_effective_wd": 6.444444444444444e-05,
      "total_wd_budget_epoch": 0.0029
    },
    {
      "epoch": 152,
      "train_loss": 0.037816148872176804,
      "test_loss": 2.3615611972808837,
      "train_acc": 99.02140299479167,
      "test_acc": 68.13,
      "lr": 0.10841254903143548,
      "mean_rho_t": 0.002173515115007519,
      "std_rho_t": 0.0011808618266498261,
      "mean_alpha_t": 0.003616602946475634,
      "mean_effective_wd": 6.444444444444444e-05,
      "total_wd_budget_epoch": 0.0029
    },
    {
      "epoch": 153,
      "train_loss": 0.0408533620260035,
      "test_loss": 2.3054355533599855,
      "train_acc": 98.92374674479167,
      "test_acc": 68.17,
      "lr": 0.10414756200855609,
      "mean_rho_t": 0.0015349571460707438,
      "std_rho_t": 0.0008085241799752983,
      "mean_alpha_t": -0.005489943084674543,
      "mean_effective_wd": 6.444444444444444e-05,
      "total_wd_budget_epoch": 0.0029
    },
    {
      "epoch": 154,
      "train_loss": 0.03587391471955925,
      "test_loss": 2.3376525714874266,
      "train_acc": 99.01529947916667,
      "test_acc": 68.37,
      "lr": 0.09995557214781617,
      "mean_rho_t": 0.002043609648866905,
      "std_rho_t": 0.001033116263297372,
      "mean_alpha_t": 0.0040047970543203365,
      "mean_effective_wd": 6.444444444444444e-05,
      "total_wd_budget_epoch": 0.0029
    },
    {
      "epoch": 155,
      "train_loss": 0.03707928901227812,
      "test_loss": 2.3245844905853272,
      "train_acc": 99.02140299479167,
      "test_acc": 68.72,
      "lr": 0.09583761375998763,
      "mean_rho_t": 0.001802029856804407,
      "std_rho_t": 0.0009507219837228427,
      "mean_alpha_t": -0.004316266102199171,
      "mean_effective_wd": 6.444444444444444e-05,
      "total_wd_budget_epoch": 0.0029
    },
    {
      "epoch": 156,
      "train_loss": 0.03422078053699806,
      "test_loss": 2.2941552467346193,
      "train_acc": 99.06412760416667,
      "test_acc": 68.49,
      "lr": 0.09179470288968435,
      "mean_rho_t": 0.0017226142959969983,
      "std_rho_t": 0.0009268067011556628,
      "mean_alpha_t": -0.006445941248128034,
      "mean_effective_wd": 6.444444444444444e-05,
      "total_wd_budget_epoch": 0.0029
    },
    {
      "epoch": 157,
      "train_loss": 0.03110922345270713,
      "test_loss": 2.3196093532562254,
      "train_acc": 99.22078450520833,
      "test_acc": 68.48,
      "lr": 0.08782783706466818,
      "mean_rho_t": 0.0013416177811495663,
      "std_rho_t": 0.0006965190827874994,
      "mean_alpha_t": -0.0038033603831976255,
      "mean_effective_wd": 6.444444444444444e-05,
      "total_wd_budget_epoch": 0.0029
    },
    {
      "epoch": 158,
      "train_loss": 0.02989406984609862,
      "test_loss": 2.379281187438965,
      "train_acc": 99.163818359375,
      "test_acc": 68.47,
      "lr": 0.08393799504972384,
      "mean_rho_t": 0.0008995335551898877,
      "std_rho_t": 0.0005323990709752642,
      "mean_alpha_t": -0.011204749233995656,
      "mean_effective_wd": 6.444444444444444e-05,
      "total_wd_budget_epoch": 0.0029
    },
    {
      "epoch": 159,
      "train_loss": 0.02606201232022916,
      "test_loss": 2.382579612350464,
      "train_acc": 99.30216471354167,
      "test_acc": 68.55,
      "lr": 0.08012613660516377,
      "mean_rho_t": 0.0011065352147854714,
      "std_rho_t": 0.0005623544727630934,
      "mean_alpha_t": -0.009610765661073762,
      "mean_effective_wd": 6.444444444444444e-05,
      "total_wd_budget_epoch": 0.0029
    },
    {
      "epoch": 160,
      "train_loss": 0.027091723090658586,
      "test_loss": 2.406581303405762,
      "train_acc": 99.285888671875,
      "test_acc": 68.41,
      "lr": 0.07639320225002107,
      "mean_rho_t": 0.0014742261796517307,
      "std_rho_t": 0.0006664433575817299,
      "mean_alpha_t": -6.687259855350946e-05,
      "mean_effective_wd": 6.444444444444444e-05,
      "total_wd_budget_epoch": 0.0029
    },
    {
      "epoch": 161,
      "train_loss": 0.026915592102644343,
      "test_loss": 2.3604267322540284,
      "train_acc": 99.285888671875,
      "test_acc": 68.45,
      "lr": 0.07274011302999069,
      "mean_rho_t": 0.0009833092040819071,
      "std_rho_t": 0.0004514830719945116,
      "mean_alpha_t": -0.005834308307377286,
      "mean_effective_wd": 6.444444444444444e-05,
      "total_wd_budget_epoch": 0.0029
    },
    {
      "epoch": 162,
      "train_loss": 0.02440790944577505,
      "test_loss": 2.3812928268432616,
      "train_acc": 99.39778645833333,
      "test_acc": 68.64,
      "lr": 0.06916777029017532,
      "mean_rho_t": 0.0017112417079119776,
      "std_rho_t": 0.0008140358152476507,
      "mean_alpha_t": 0.00535975482827645,
      "mean_effective_wd": 6.444444444444444e-05,
      "total_wd_budget_epoch": 0.0029
    },
    {
      "epoch": 163,
      "train_loss": 0.02385708214327072,
      "test_loss": 2.405881478881836,
      "train_acc": 99.37947591145833,
      "test_acc": 68.39,
      "lr": 0.06567705545269198,
      "mean_rho_t": 0.0016725670773171475,
      "std_rho_t": 0.0008138977040757914,
      "mean_alpha_t": 0.0061110555439561395,
      "mean_effective_wd": 6.444444444444444e-05,
      "total_wd_budget_epoch": 0.0029
    },
    {
      "epoch": 164,
      "train_loss": 0.02305121176565687,
      "test_loss": 2.432691425704956,
      "train_acc": 99.41609700520833,
      "test_acc": 68.84,
      "lr": 0.06226882979919406,
      "mean_rho_t": 0.0014715161302866887,
      "std_rho_t": 0.000755620138475057,
      "mean_alpha_t": 0.008091102056964013,
      "mean_effective_wd": 6.444444444444444e-05,
      "total_wd_budget_epoch": 0.0029
    },
    {
      "epoch": 165,
      "train_loss": 0.021905120947243024,
      "test_loss": 2.453832942199707,
      "train_acc": 99.420166015625,
      "test_acc": 68.66,
      "lr": 0.05894393425836322,
      "mean_rho_t": 0.0011339714488884892,
      "std_rho_t": 0.0005868790394182657,
      "mean_alpha_t": 0.010523454334449817,
      "mean_effective_wd": 6.444444444444444e-05,
      "total_wd_budget_epoch": 0.0029
    },
    {
      "epoch": 166,
      "train_loss": 0.01964333681583715,
      "test_loss": 2.485951612472534,
      "train_acc": 99.44254557291667,
      "test_acc": 68.72,
      "lr": 0.0557031891984225,
      "mean_rho_t": 0.0008326727230712051,
      "std_rho_t": 0.0004215733200166832,
      "mean_alpha_t": -0.0056555284019287186,
      "mean_effective_wd": 6.444444444444444e-05,
      "total_wd_budget_epoch": 0.0029
    },
    {
      "epoch": 167,
      "train_loss": 0.022090021326827507,
      "test_loss": 2.524970139312744,
      "train_acc": 99.45475260416667,
      "test_acc": 68.67,
      "lr": 0.05254739422472348,
      "mean_rho_t": 0.0009744709546635513,
      "std_rho_t": 0.0005640597728008076,
      "mean_alpha_t": -0.006725350868345668,
      "mean_effective_wd": 6.444444444444444e-05,
      "total_wd_budget_epoch": 0.0029
    },
    {
      "epoch": 168,
      "train_loss": 0.01938997965771705,
      "test_loss": 2.495623139190674,
      "train_acc": 99.48933919270833,
      "test_acc": 68.8,
      "lr": 0.04947732798245457,
      "mean_rho_t": 0.0010013689666990178,
      "std_rho_t": 0.0005282578790378264,
      "mean_alpha_t": 0.005392194708223256,
      "mean_effective_wd": 6.444444444444444e-05,
      "total_wd_budget_epoch": 0.0029
    },
    {
      "epoch": 169,
      "train_loss": 0.01988592600294699,
      "test_loss": 2.5177335704803467,
      "train_acc": 99.45882161458333,
      "test_acc": 68.66,
      "lr": 0.046493747964522616,
      "mean_rho_t": 0.0024132920450707462,
      "std_rho_t": 0.00111572711662931,
      "mean_alpha_t": 0.0012387614697123399,
      "mean_effective_wd": 6.444444444444444e-05,
      "total_wd_budget_epoch": 0.0029
    },
    {
      "epoch": 170,
      "train_loss": 0.018671572557650506,
      "test_loss": 2.4933117015838624,
      "train_acc": 99.47509765625,
      "test_acc": 68.78,
      "lr": 0.04359739032465289,
      "mean_rho_t": 0.0013952290366123163,
      "std_rho_t": 0.0007379874380931096,
      "mean_alpha_t": 0.004231744303260771,
      "mean_effective_wd": 6.444444444444444e-05,
      "total_wd_budget_epoch": 0.0029
    },
    {
      "epoch": 171,
      "train_loss": 0.019599846564233303,
      "test_loss": 2.493314599990845,
      "train_acc": 99.52392578125,
      "test_acc": 68.98,
      "lr": 0.04078896969575379,
      "mean_rho_t": 0.0006730149030023759,
      "std_rho_t": 0.00031063104567156995,
      "mean_alpha_t": 0.0033323672166751706,
      "mean_effective_wd": 6.444444444444444e-05,
      "total_wd_budget_epoch": 0.0029
    },
    {
      "epoch": 172,
      "train_loss": 0.01756025480184083,
      "test_loss": 2.5061170848846435,
      "train_acc": 99.52392578125,
      "test_acc": 69.17,
      "lr": 0.03806917901359226,
      "mean_rho_t": 0.0007436332099173442,
      "std_rho_t": 0.0003877658790220721,
      "mean_alpha_t": -0.0005635171206901333,
      "mean_effective_wd": 6.444444444444444e-05,
      "total_wd_budget_epoch": 0.0029
    },
    {
      "epoch": 173,
      "train_loss": 0.015399835237379497,
      "test_loss": 2.504089041519165,
      "train_acc": 99.59716796875,
      "test_acc": 68.93,
      "lr": 0.03543868934582197,
      "mean_rho_t": 0.0009149075520604958,
      "std_rho_t": 0.0005571747824269922,
      "mean_alpha_t": -0.0005586530710327254,
      "mean_effective_wd": 6.444444444444444e-05,
      "total_wd_budget_epoch": 0.0029
    },
    {
      "epoch": 174,
      "train_loss": 0.01594715107542773,
      "test_loss": 2.511093474197388,
      "train_acc": 99.55037434895833,
      "test_acc": 69.06,
      "lr": 0.03289814972640764,
      "mean_rho_t": 0.0008697146977208046,
      "std_rho_t": 0.00046685951917170126,
      "mean_alpha_t": -0.001582855920197475,
      "mean_effective_wd": 6.444444444444444e-05,
      "total_wd_budget_epoch": 0.0029
    },
    {
      "epoch": 175,
      "train_loss": 0.016564199312900502,
      "test_loss": 2.5376559619903563,
      "train_acc": 99.57275390625,
      "test_acc": 68.86,
      "lr": 0.030448186995485394,
      "mean_rho_t": 0.0023284722861177305,
      "std_rho_t": 0.0010271093442915024,
      "mean_alpha_t": 0.004643501145211146,
      "mean_effective_wd": 6.444444444444444e-05,
      "total_wd_budget_epoch": 0.0029
    },
    {
      "epoch": 176,
      "train_loss": 0.015779066083875175,
      "test_loss": 2.549087236404419,
      "train_acc": 99.57275390625,
      "test_acc": 68.75,
      "lr": 0.028089405644699462,
      "mean_rho_t": 0.0011170519887246685,
      "std_rho_t": 0.0005324175898237423,
      "mean_alpha_t": 0.002782357264463717,
      "mean_effective_wd": 6.444444444444444e-05,
      "total_wd_budget_epoch": 0.0029
    },
    {
      "epoch": 177,
      "train_loss": 0.01448718500129568,
      "test_loss": 2.5450522369384765,
      "train_acc": 99.61751302083333,
      "test_acc": 69.0,
      "lr": 0.02582238766805305,
      "mean_rho_t": 0.0011955948123918273,
      "std_rho_t": 0.0005871056020017582,
      "mean_alpha_t": -0.00033212422383709854,
      "mean_effective_wd": 6.444444444444444e-05,
      "total_wd_budget_epoch": 0.0029
    },
    {
      "epoch": 178,
      "train_loss": 0.01819889738302057,
      "test_loss": 2.5569983306884767,
      "train_acc": 99.53409830729167,
      "test_acc": 69.0,
      "lr": 0.02364769241830982,
      "mean_rho_t": 0.0015018396254703062,
      "std_rho_t": 0.0007381941689043205,
      "mean_alpha_t": 0.003954091240284905,
      "mean_effective_wd": 6.444444444444444e-05,
      "total_wd_budget_epoch": 0.0029
    },
    {
      "epoch": 179,
      "train_loss": 0.014639334612487195,
      "test_loss": 2.546177518463135,
      "train_acc": 99.63582356770833,
      "test_acc": 68.9,
      "lr": 0.021565856468981882,
      "mean_rho_t": 0.0010980090650176179,
      "std_rho_t": 0.0005401322118405108,
      "mean_alpha_t": -0.0014751369325989555,
      "mean_effective_wd": 6.444444444444444e-05,
      "total_wd_budget_epoch": 0.0029
    },
    {
      "epoch": 180,
      "train_loss": 0.012713279468395436,
      "test_loss": 2.5594733573913575,
      "train_acc": 99.676513671875,
      "test_acc": 69.11,
      "lr": 0.019577393481938588,
      "mean_rho_t": 0.0007084121395444758,
      "std_rho_t": 0.0004035366649874258,
      "mean_alpha_t": -0.007869221612318374,
      "mean_effective_wd": 6.444444444444444e-05,
      "total_wd_budget_epoch": 0.0029
    },
    {
      "epoch": 181,
      "train_loss": 0.014603222991960743,
      "test_loss": 2.54948821144104,
      "train_acc": 99.59920247395833,
      "test_acc": 69.01,
      "lr": 0.017682794080667953,
      "mean_rho_t": 0.0016589944157879954,
      "std_rho_t": 0.000869177011078695,
      "mean_alpha_t": -0.000901607220487991,
      "mean_effective_wd": 6.444444444444444e-05,
      "total_wd_budget_epoch": 0.0029
    },
    {
      "epoch": 182,
      "train_loss": 0.014638551995934298,
      "test_loss": 2.5692094551086426,
      "train_acc": 99.603271484375,
      "test_acc": 69.01,
      "lr": 0.01588252572922282,
      "mean_rho_t": 0.000937064366998408,
      "std_rho_t": 0.00048255775118585933,
      "mean_alpha_t": 0.0035990387050907832,
      "mean_effective_wd": 6.444444444444444e-05,
      "total_wd_budget_epoch": 0.0029
    },
    {
      "epoch": 183,
      "train_loss": 0.011577878836154317,
      "test_loss": 2.572689960479736,
      "train_acc": 99.68668619791667,
      "test_acc": 69.11,
      "lr": 0.014177032616880815,
      "mean_rho_t": 0.000383178938396654,
      "std_rho_t": 0.00019023327623264924,
      "mean_alpha_t": -0.008035998162083922,
      "mean_effective_wd": 6.444444444444444e-05,
      "total_wd_budget_epoch": 0.0029
    },
    {
      "epoch": 184,
      "train_loss": 0.013532283114424596,
      "test_loss": 2.5672141174316407,
      "train_acc": 99.64192708333333,
      "test_acc": 68.96,
      "lr": 0.012566735548547614,
      "mean_rho_t": 0.0014787033314799208,
      "std_rho_t": 0.0007580339596329045,
      "mean_alpha_t": 0.0038701039181281136,
      "mean_effective_wd": 6.444444444444444e-05,
      "total_wd_budget_epoch": 0.0029
    },
    {
      "epoch": 185,
      "train_loss": 0.013470547593897209,
      "test_loss": 2.5850854698181154,
      "train_acc": 99.67041015625,
      "test_acc": 69.06,
      "lr": 0.011052031840929379,
      "mean_rho_t": 0.0007674525442589854,
      "std_rho_t": 0.00041580742356787335,
      "mean_alpha_t": -0.003949986935949801,
      "mean_effective_wd": 6.444444444444444e-05,
      "total_wd_budget_epoch": 0.0029
    },
    {
      "epoch": 186,
      "train_loss": 0.011804096488049254,
      "test_loss": 2.600930859375,
      "train_acc": 99.66634114583333,
      "test_acc": 69.17,
      "lr": 0.00963329522450107,
      "mean_rho_t": 0.0007396218149371309,
      "std_rho_t": 0.0005281999967360482,
      "mean_alpha_t": 0.007645488310639058,
      "mean_effective_wd": 6.444444444444444e-05,
      "total_wd_budget_epoch": 0.0029
    },
    {
      "epoch": 187,
      "train_loss": 0.01448280939560694,
      "test_loss": 2.5962200897216796,
      "train_acc": 99.61751302083333,
      "test_acc": 69.14,
      "lr": 0.008310875751293656,
      "mean_rho_t": 0.0009037407502550852,
      "std_rho_t": 0.00044317044400216186,
      "mean_alpha_t": 0.005654513604916519,
      "mean_effective_wd": 6.444444444444444e-05,
      "total_wd_budget_epoch": 0.0029
    },
    {
      "epoch": 188,
      "train_loss": 0.012881406689605987,
      "test_loss": 2.5708432060241697,
      "train_acc": 99.664306640625,
      "test_acc": 69.06,
      "lr": 0.007085099708524512,
      "mean_rho_t": 0.0015481924643549647,
      "std_rho_t": 0.0007596077185300936,
      "mean_alpha_t": -0.0010566013713553314,
      "mean_effective_wd": 6.444444444444444e-05,
      "total_wd_budget_epoch": 0.0029
    },
    {
      "epoch": 189,
      "train_loss": 0.014260225250230482,
      "test_loss": 2.5655279567718505,
      "train_acc": 99.62361653645833,
      "test_acc": 69.05,
      "lr": 0.005956269538090453,
      "mean_rho_t": 0.0013172232201968768,
      "std_rho_t": 0.0006256469293117394,
      "mean_alpha_t": -0.005849800246528869,
      "mean_effective_wd": 6.444444444444444e-05,
      "total_wd_budget_epoch": 0.0029
    },
    {
      "epoch": 190,
      "train_loss": 0.011615817211956406,
      "test_loss": 2.587555711746216,
      "train_acc": 99.700927734375,
      "test_acc": 69.04,
      "lr": 0.004924663761944937,
      "mean_rho_t": 0.0010625189219310217,
      "std_rho_t": 0.0004779378358687936,
      "mean_alpha_t": 0.004862525546763231,
      "mean_effective_wd": 6.444444444444444e-05,
      "total_wd_budget_epoch": 0.0029
    },
    {
      "epoch": 191,
      "train_loss": 0.010966512151450539,
      "test_loss": 2.5768718715667727,
      "train_acc": 99.70296223958333,
      "test_acc": 69.14,
      "lr": 0.003990536913376985,
      "mean_rho_t": 0.0009762726016681847,
      "std_rho_t": 0.00044760506984191855,
      "mean_alpha_t": -0.010170322914251005,
      "mean_effective_wd": 6.444444444444444e-05,
      "total_wd_budget_epoch": 0.0029
    },
    {
      "epoch": 192,
      "train_loss": 0.01142316266001823,
      "test_loss": 2.566262287139893,
      "train_acc": 99.688720703125,
      "test_acc": 69.07,
      "lr": 0.0031541194742088943,
      "mean_rho_t": 0.0007364016525220979,
      "std_rho_t": 0.00037706310951343436,
      "mean_alpha_t": 0.0008574248569228762,
      "mean_effective_wd": 6.444444444444444e-05,
      "total_wd_budget_epoch": 0.0029
    },
    {
      "epoch": 193,
      "train_loss": 0.012861164369193526,
      "test_loss": 2.5699655349731447,
      "train_acc": 99.66023763020833,
      "test_acc": 69.05,
      "lr": 0.002415617817928162,
      "mean_rho_t": 0.0010713251463043687,
      "std_rho_t": 0.0004894882102551454,
      "mean_alpha_t": 0.0017675511449199094,
      "mean_effective_wd": 6.444444444444444e-05,
      "total_wd_budget_epoch": 0.0029
    },
    {
      "epoch": 194,
      "train_loss": 0.011790750460932031,
      "test_loss": 2.5971402088165285,
      "train_acc": 99.70906575520833,
      "test_acc": 68.96,
      "lr": 0.0017752141587680016,
      "mean_rho_t": 0.0010667397653341504,
      "std_rho_t": 0.00044674501110228225,
      "mean_alpha_t": -0.0038506514428378923,
      "mean_effective_wd": 6.444444444444444e-05,
      "total_wd_budget_epoch": 0.0029
    },
    {
      "epoch": 195,
      "train_loss": 0.011547912853226686,
      "test_loss": 2.580952734375,
      "train_acc": 99.688720703125,
      "test_acc": 69.05,
      "lr": 0.0012330665067488145,
      "mean_rho_t": 0.00082549450220391,
      "std_rho_t": 0.00045503725503212735,
      "mean_alpha_t": -0.010230842535577284,
      "mean_effective_wd": 6.444444444444444e-05,
      "total_wd_budget_epoch": 0.0029
    },
    {
      "epoch": 196,
      "train_loss": 0.010901515338143023,
      "test_loss": 2.5910558792114258,
      "train_acc": 99.73551432291667,
      "test_acc": 69.06,
      "lr": 0.0007893086286913765,
      "mean_rho_t": 0.0014309677245183633,
      "std_rho_t": 0.0007232893680144705,
      "mean_alpha_t": -0.002797237554380787,
      "mean_effective_wd": 6.444444444444444e-05,
      "total_wd_budget_epoch": 0.0029
    },
    {
      "epoch": 197,
      "train_loss": 0.01191182661568746,
      "test_loss": 2.5861681076049803,
      "train_acc": 99.70906575520833,
      "test_acc": 69.16,
      "lr": 0.0004440500152120386,
      "mean_rho_t": 0.0014896869739185288,
      "std_rho_t": 0.0008027808001887545,
      "mean_alpha_t": -0.00330036273953811,
      "mean_effective_wd": 6.444444444444444e-05,
      "total_wd_budget_epoch": 0.0029
    },
    {
      "epoch": 198,
      "train_loss": 0.011107640612560013,
      "test_loss": 2.5699933864593505,
      "train_acc": 99.70703125,
      "test_acc": 69.11,
      "lr": 0.00019737585370736,
      "mean_rho_t": 0.0012824960484595297,
      "std_rho_t": 0.0005811392952204599,
      "mean_alpha_t": 0.0010444373297185444,
      "mean_effective_wd": 6.444444444444444e-05,
      "total_wd_budget_epoch": 0.0029
    },
    {
      "epoch": 199,
      "train_loss": 0.012181647985319918,
      "test_loss": 2.5674232723236083,
      "train_acc": 99.64599609375,
      "test_acc": 69.04,
      "lr": 4.934700733576492e-05,
      "mean_rho_t": 0.0010920134380706982,
      "std_rho_t": 0.0005514194816386262,
      "mean_alpha_t": -0.006627745971323376,
      "mean_effective_wd": 6.444444444444444e-05,
      "total_wd_budget_epoch": 0.0029
    }
  ]
}