{
  "task_id": "p2_causal",
  "device": "cuda",
  "gpu_id": "3",
  "seed": 42,
  "start_time": "2026-04-28T00:22:52.017087",
  "sae_configs": {
    "high_k": {
      "k": 100,
      "d_sae": 8192,
      "training_tokens": 500000,
      "absorption_rate": 0.19230769230769232
    },
    "low_k": {
      "k": 10,
      "d_sae": 8192,
      "training_tokens": 500000,
      "absorption_rate": 0.4230769230769231
    }
  },
  "probe_results": {
    "high_k": {
      "train_acc": 1.0,
      "test_acc": 0.1
    },
    "low_k": {
      "train_acc": 0.9875,
      "test_acc": 0.1
    }
  },
  "correlation_direction": "positive",
  "correlation_magnitude": 0.0,
  "elapsed_seconds": 58.659788846969604,
  "end_time": "2026-04-28T00:23:50.676813"
}